{
    "inputUrl": "https://www.instagram.com/_urvashi_lalwani_",
    "id": "32419739756",
    "username": "_urvashi_lalwani_",
    "url": "https://www.instagram.com/_urvashi_lalwani_",
    "fullName": "\ud835\ude50\ud835\ude67\ud835\ude6b\ud835\ude56\ud835\ude68\ud835\ude5d\ud835\ude5e \ud835\ude47\ud835\ude56\ud835\ude61\ud835\ude6c\ud835\ude56\ud835\ude63\ud835\ude5e",
    "biography": "\ud83e\udda2 \ud835\ude3c \ud835\ude57\ud835\ude5e\ud835\ude69 \ud835\ude64\ud835\ude5b \ud835\ude5a\ud835\ude6b\ud835\ude5a\ud835\ude67\ud835\ude6e\ud835\ude69\ud835\ude5d\ud835\ude5e\ud835\ude63\ud835\ude5c \n\ud83d\udc8c\ud835\ude3f\ud835\ude62 /\ud835\ude62\ud835\ude56\ud835\ude5e\ud835\ude61 \ud835\ude5b\ud835\ude64\ud835\ude67 \ud835\ude58\ud835\ude64\ud835\ude61\ud835\ude61\ud835\ude56\ud835\ude57\ud835\ude64\ud835\ude67\ud835\ude56\ud835\ude69\ud835\ude5e\ud835\ude64\ud835\ude63\n\u2728Skincare | Makeup | Fashion\n\ud83d\udccdMumbai",
    "externalUrls": [
        {
            "title": "",
            "lynx_url": "https://l.instagram.com/?u=http%3A%2F%2Fwishlink.com%2Furvashilalwani&e=AT2gnDABtVT5yrM3tbTbjoP0LMeyQtu1xBiyLSOvF_brzWP-9wjC_fjpa9T8PVaBHLc57xA-dQUnGv2a4iTYBieSucVPx47I",
            "url": "http://wishlink.com/urvashilalwani",
            "link_type": "external"
        },
        {
            "title": "Youtube channel",
            "lynx_url": "https://l.instagram.com/?u=https%3A%2F%2Fyoutube.com%2F%40_urvashi_lalwani_%3Fsi%3DVKSBB4FKooheLJxS&e=AT0rrul4eG9D6eaTNIUei5z74aEuz5gv1SITnkBooYuZgReSkMRmW9yk9_NfqlUH9dvqYO_0ihfoQe66Vaw5Xu4La4bb1pRy",
            "url": "https://youtube.com/@_urvashi_lalwani_?si=VKSBB4FKooheLJxS",
            "link_type": "external"
        },
        {
            "title": "Get to know all about Content Creation",
            "lynx_url": "https://l.instagram.com/?u=http%3A%2F%2Ftopmate.io%2Furvashi_lalwani%2F%3Futm_source%3Dtopmate%26utm_medium%3Dpopup%26utm_campaign%3DPage_Ready&e=AT3Pxhp-3S8CfGEZZyX4yO_n1TYviXX0fAmln4B00mVMpnlxf6JymeN8bIwWpl5jkYAUw6VYdkYAiu_TjhBJqtn5Q4ReohJ4",
            "url": "http://topmate.io/urvashi_lalwani/?utm_source=topmate&utm_medium=popup&utm_campaign=Page_Ready",
            "link_type": "external"
        }
    ],
    "externalUrl": "http://wishlink.com/urvashilalwani",
    "externalUrlShimmed": "https://l.instagram.com/?u=http%3A%2F%2Fwishlink.com%2Furvashilalwani&e=AT0cZadpQJCoH2pdVJLGSHqGtGZXREHdldPIzSvNpI7xJVCSzcVIR9X47kpFiGlrBTRPmHrd7sQZVwsD8wuqaCI2mZke6hso",
    "followersCount": 18203,
    "followsCount": 1570,
    "hasChannel": false,
    "highlightReelCount": 23,
    "isBusinessAccount": false,
    "joinedRecently": false,
    "businessCategoryName": "Digital creator",
    "private": false,
    "verified": false,
    "profilePicUrl": "https://instagram.fbhk1-3.fna.fbcdn.net/v/t51.2885-19/470942773_2947884075359904_2739952270229671305_n.jpg?stp=dst-jpg_e0_s150x150_tt6&_nc_ht=instagram.fbhk1-3.fna.fbcdn.net&_nc_cat=100&_nc_oc=Q6cZ2QHHpibXBwkkYREhypZpew140bZPQbx9vFpJmgGXlquy5XXQR0SASXlUhAxAvHtaiT0&_nc_ohc=pORn0uj7IggQ7kNvwFYAXK2&_nc_gid=e5mGv2vdFcvv89Ua151bSA&edm=AOQ1c0wBAAAA&ccb=7-5&oh=00_AfMVNzDLuLXdsyY96KJ6EOB4nGZeEjqpaBamE2CDMXby0Q&oe=684EDD37&_nc_sid=8b3546",
    "profilePicUrlHD": "https://instagram.fbhk1-3.fna.fbcdn.net/v/t51.2885-19/470942773_2947884075359904_2739952270229671305_n.jpg?stp=dst-jpg_s320x320_tt6&_nc_ht=instagram.fbhk1-3.fna.fbcdn.net&_nc_cat=100&_nc_oc=Q6cZ2QHHpibXBwkkYREhypZpew140bZPQbx9vFpJmgGXlquy5XXQR0SASXlUhAxAvHtaiT0&_nc_ohc=pORn0uj7IggQ7kNvwFYAXK2&_nc_gid=e5mGv2vdFcvv89Ua151bSA&edm=AOQ1c0wBAAAA&ccb=7-5&oh=00_AfOWJGDwdbfKt2ySZ-qEiQQGcFeIXiKQXP-6pqO9Fkyowg&oe=684EDD37&_nc_sid=8b3546",
    "igtvVideoCount": 32,
    "relatedProfiles": [],
    "latestIgtvVideos": [
        {
            "type": "Video",
            "shortCode": "Cb7q0PLAC5P",
            "title": "",
            "caption": "\u2728 GIVEAWAY CLOSED\u2728\n2 winners will receive hampers \ud83d\ude0d\n\n[Rules]\n\n\ud83c\udf52 Follow @_urvashi_lalwani_ \n\ud83c\udf52 \u2018Turn On\u2019 post notifications for my profiles (click on \u2022\u2022\u2022 on the top right of this post) \ud83e\udd70\n\ud83c\udf52Add me to your Favourites\n\ud83c\udf52 Tag 3 girlfriends in the comments below \ud83d\udc47\n\ud83c\udf52Subscribe to my youtube channel (link in bio)\n\ud83c\udf52 Brownie points for engaging with my daily content and sharing your favourite reels on your story \ud83d\ude0d\n.\n.\n.\n.\n- Winners to be announced on 30th of April, 2022.\n- DO NOT DM/Mail about making you a winner, this will lead to immediate disqualification.\n- Giveaway accounts will not eligible for this .\n- This is open for Indian Residents only.\n- This giveaway is not sponsored by any of the brands mentioned above.\n.\n.\n#reels #trendingsongs #darshanraval #viralvideos #makeup #explorepage #sironagotyourback #maybelline #freeproducts #urvashilalwani #reeloftheday #reelstrending #reelkarofeelkaro\u2764 #reelsofinstagram #SironaGotYourBack #SironaPMSBuddy #selflove #Women\u2019sDaywithSirona #SironaWomenPower #SironaGotYourback #Women'sDaywithSirona",
            "commentsCount": 26,
            "commentsDisabled": false,
            "dimensionsHeight": 750,
            "dimensionsWidth": 750,
            "displayUrl": "https://instagram.fbhk1-2.fna.fbcdn.net/v/t51.2885-15/277821332_170147805349894_5303166837944062612_n.jpg?stp=dst-jpg_e15_tt6&_nc_ht=instagram.fbhk1-2.fna.fbcdn.net&_nc_cat=110&_nc_oc=Q6cZ2QHHpibXBwkkYREhypZpew140bZPQbx9vFpJmgGXlquy5XXQR0SASXlUhAxAvHtaiT0&_nc_ohc=eqShYZtoDzkQ7kNvwG1amPU&_nc_gid=e5mGv2vdFcvv89Ua151bSA&edm=AOQ1c0wBAAAA&ccb=7-5&oh=00_AfPaImpuT6cB8hP2-VIlhKHbzjBc5_Y2fHvZYNgHPpp6KA&oe=684F06DD&_nc_sid=8b3546",
            "likesCount": 63,
            "videoDuration": 15.4,
            "videoViewCount": 2878,
            "id": "2809027100252581455",
            "hashtags": [
                "reels",
                "trendingsongs",
                "darshanraval",
                "viralvideos",
                "makeup",
                "explorepage",
                "sironagotyourback",
                "maybelline",
                "freeproducts",
                "urvashilalwani",
                "reeloftheday",
                "reelstrending",
                "reelkarofeelkaro\u2764",
                "reelsofinstagram",
                "SironaGotYourBack",
                "SironaPMSBuddy",
                "selflove",
                "Women\u2019sDaywithSirona",
                "SironaWomenPower",
                "SironaGotYourback",
                "Women'sDaywithSirona"
            ],
            "mentions": [
                "_urvashi_lalwani_"
            ],
            "url": "https://www.instagram.com/p/Cb7q0PLAC5P/",
            "firstComment": "",
            "latestComments": [],
            "images": [],
            "videoUrl": "https://instagram.fbhk1-4.fna.fbcdn.net/o1/v/t16/f2/m69/AQNZp6c7MfiaaWVHrs_sz_YxXQsnpl-1nyPOffdFSMzG_K_dyf1HohUXi8KyPSqQqvCfHo8Ic1v4dOf70bklpDQp.mp4?stp=dst-mp4&efg=eyJxZV9ncm91cHMiOiJbXCJpZ193ZWJfZGVsaXZlcnlfdnRzX290ZlwiXSIsInZlbmNvZGVfdGFnIjoidnRzX3ZvZF91cmxnZW4uaWd0di5jMi43MjAuYmFzZWxpbmUifQ&_nc_cat=107&vs=522060029551242_1109077397&_nc_vs=HBksFQIYOnBhc3N0aHJvdWdoX2V2ZXJzdG9yZS9HTWY0aUJDVS1IUnRYOVlCQUx3dW80RzN1RzBMYnZWQkFBQUYVAALIARIAFQIYOnBhc3N0aHJvdWdoX2V2ZXJzdG9yZS9HTlRNaXhCVV9BU1BIOVVCQUhESUt2Mkthd1pBYnZWQkFBQUYVAgLIARIAKAAYABsBiAd1c2Vfb2lsATEVAAAm5vj46Lzv%2FUAVAigCQzMsF0AuzMzMzMzNGBJkYXNoX2Jhc2VsaW5lXzFfdjERAHXsB2XCngEA&ccb=9-4&oh=00_AfMUAuqUjofGlA7cvn0RHypRaNkkKXEjH5aZ3NF3IR200Q&oe=684AF863&_nc_sid=8b3546",
            "alt": null,
            "timestamp": "2022-04-04T14:23:04.000Z",
            "childPosts": [],
            "ownerUsername": "_urvashi_lalwani_",
            "ownerId": "32419739756",
            "productType": "igtv",
            "taggedUsers": [
                {
                    "full_name": "\ud835\ude50\ud835\ude67\ud835\ude6b\ud835\ude56\ud835\ude68\ud835\ude5d\ud835\ude5e \ud835\ude47\ud835\ude56\ud835\ude61\ud835\ude6c\ud835\ude56\ud835\ude63\ud835\ude5e",
                    "id": "32419739756",
                    "is_verified": false,
                    "profile_pic_url": "https://instagram.fbhk1-3.fna.fbcdn.net/v/t51.2885-19/470942773_2947884075359904_2739952270229671305_n.jpg?stp=dst-jpg_e0_s150x150_tt6&_nc_ht=instagram.fbhk1-3.fna.fbcdn.net&_nc_cat=100&_nc_oc=Q6cZ2QHHpibXBwkkYREhypZpew140bZPQbx9vFpJmgGXlquy5XXQR0SASXlUhAxAvHtaiT0&_nc_ohc=pORn0uj7IggQ7kNvwFYAXK2&_nc_gid=e5mGv2vdFcvv89Ua151bSA&edm=AOQ1c0wBAAAA&ccb=7-5&oh=00_AfMVNzDLuLXdsyY96KJ6EOB4nGZeEjqpaBamE2CDMXby0Q&oe=684EDD37&_nc_sid=8b3546",
                    "username": "_urvashi_lalwani_"
                }
            ],
            "isCommentsDisabled": false
        },
        {
            "type": "Video",
            "shortCode": "CbcDaHMrn77",
            "title": "",
            "caption": "To allow myself big relief from the period pain, I resorted to #SironaPMSBuddy and popping its Gummies while I'm PMSing has brought me great comfort! PMS Gummies- Sirona PMS gummies are natural and infused with natural actives to help relieve the symptoms of PMS (Premenstrual Syndrome). - Soothes cramps - Elevates mood - Helps debloat - Reduces hormonal acne . . . . . . @sironahygiene @goodcreatorco #SironaGotYourBack #SironaPMSBuddy #selflove #Women\u2019sDaywithSirona #SironaWomenPower @goodcreatorco #SironaGotYourback #Women'sDaywithSirona",
            "commentsCount": 2,
            "commentsDisabled": false,
            "dimensionsHeight": 750,
            "dimensionsWidth": 750,
            "displayUrl": "https://instagram.fbhk1-4.fna.fbcdn.net/v/t51.2885-15/276968019_479042163888631_1577745224351489652_n.jpg?stp=dst-jpg_e15_tt6&_nc_ht=instagram.fbhk1-4.fna.fbcdn.net&_nc_cat=107&_nc_oc=Q6cZ2QHHpibXBwkkYREhypZpew140bZPQbx9vFpJmgGXlquy5XXQR0SASXlUhAxAvHtaiT0&_nc_ohc=03gnCv6SL18Q7kNvwEX0FWY&_nc_gid=e5mGv2vdFcvv89Ua151bSA&edm=AOQ1c0wBAAAA&ccb=7-5&oh=00_AfM-o5O4nliw_iphn1coAYb4SXtjV-4-Pb4pQpxGJ-HZ0g&oe=684F0524&_nc_sid=8b3546",
            "likesCount": 92,
            "videoDuration": 1.733,
            "videoViewCount": 9898,
            "id": "2800128056892489467",
            "hashtags": [
                "SironaPMSBuddy",
                "SironaGotYourBack",
                "selflove",
                "Women\u2019sDaywithSirona",
                "SironaWomenPower",
                "SironaGotYourback",
                "Women'sDaywithSirona"
            ],
            "mentions": [
                "sironahygiene",
                "goodcreatorco"
            ],
            "url": "https://www.instagram.com/p/CbcDaHMrn77/",
            "firstComment": "",
            "latestComments": [],
            "images": [],
            "videoUrl": "https://instagram.fbhk1-2.fna.fbcdn.net/o1/v/t16/f2/m69/AQOaFkv8-o8SVkh3vtAtHTVsqtOREUiNSlLQQ-3wZBs1tlEPWtfBal50Nmo9LOTjlFxUmjwlWmrVQF6vPV1TOAVs.mp4?stp=dst-mp4&efg=eyJxZV9ncm91cHMiOiJbXCJpZ193ZWJfZGVsaXZlcnlfdnRzX290ZlwiXSIsInZlbmNvZGVfdGFnIjoidnRzX3ZvZF91cmxnZW4uaWd0di5jMi43MjAuYmFzZWxpbmUifQ&_nc_cat=110&vs=1012359086305252_572832063&_nc_vs=HBksFQIYOnBhc3N0aHJvdWdoX2V2ZXJzdG9yZS9HSmktZ3hCa1JGUzYyMkVBQU90Sl8xNWNmOE5wYnZWQkFBQUYVAALIARIAFQIYOnBhc3N0aHJvdWdoX2V2ZXJzdG9yZS9HS3lVZ3hBNFhGaF96VTRCQUhwSWZhLXYzOGtTYnZWQkFBQUYVAgLIARIAKAAYABsBiAd1c2Vfb2lsATEVAAAmoPnj1dSZ1D8VAigCQzMsFz%2F7ul41P3zuGBJkYXNoX2Jhc2VsaW5lXzFfdjERAHXsB2XCngEA&ccb=9-4&oh=00_AfMdp2EgRS3W5Yil7P--LrFiWm_XuMmJ2CpPnngB0vSsEQ&oe=684AE41A&_nc_sid=8b3546",
            "alt": null,
            "timestamp": "2022-03-23T07:42:18.000Z",
            "childPosts": [],
            "ownerUsername": "_urvashi_lalwani_",
            "ownerId": "32419739756",
            "productType": "igtv",
            "taggedUsers": [
                {
                    "full_name": "Sirona Hygiene",
                    "id": "3536384090",
                    "is_verified": true,
                    "profile_pic_url": "https://instagram.fbhk1-3.fna.fbcdn.net/v/t51.2885-19/410722672_2379086218964944_6620612575169273744_n.jpg?stp=dst-jpg_e0_s150x150_tt6&_nc_ht=instagram.fbhk1-3.fna.fbcdn.net&_nc_cat=104&_nc_oc=Q6cZ2QHHpibXBwkkYREhypZpew140bZPQbx9vFpJmgGXlquy5XXQR0SASXlUhAxAvHtaiT0&_nc_ohc=g7_hk-bIdKEQ7kNvwGhxu4X&_nc_gid=e5mGv2vdFcvv89Ua151bSA&edm=AOQ1c0wBAAAA&ccb=7-5&oh=00_AfPIKL8BtlebjzsdbPc57E4RHppO1D5xWRXsHUEtvqAEfw&oe=684ED856&_nc_sid=8b3546",
                    "username": "sironahygiene"
                }
            ],
            "isCommentsDisabled": false
        },
        {
            "type": "Video",
            "shortCode": "CYBtWObJJqX",
            "title": "",
            "caption": "Pink eyes with @plixxo and @myglamm \n\n \n#makeup #makeuplook #makeuptherapy #makeuptutorial #easylook #muasunder5k #explore #explorepage #trending #trendingvideos #makeuptutorial #easymakeuptutorial #easymakeup #simplemakeup #wintervibes #weddingseason #maybelline #urvashilalwani",
            "commentsCount": 0,
            "commentsDisabled": false,
            "dimensionsHeight": 750,
            "dimensionsWidth": 750,
            "displayUrl": "https://instagram.fbhk1-2.fna.fbcdn.net/v/t51.29350-15/270327459_155488323481313_3091627674224685660_n.jpg?stp=dst-jpg_e35_tt6&_nc_ht=instagram.fbhk1-2.fna.fbcdn.net&_nc_cat=105&_nc_oc=Q6cZ2QHHpibXBwkkYREhypZpew140bZPQbx9vFpJmgGXlquy5XXQR0SASXlUhAxAvHtaiT0&_nc_ohc=M-xUw3RR3YIQ7kNvwGr8mmq&_nc_gid=e5mGv2vdFcvv89Ua151bSA&edm=AOQ1c0wBAAAA&ccb=7-5&oh=00_AfPdjuDwl7kIPuhibE06wD-RZvDw1MOA9Ypbb4wTqRXSBw&oe=684EEBCC&_nc_sid=8b3546",
            "likesCount": 21,
            "videoDuration": 30.7,
            "videoViewCount": 709,
            "id": "2738669487827229335",
            "hashtags": [
                "makeup",
                "makeuplook",
                "makeuptherapy",
                "makeuptutorial",
                "easylook",
                "muasunder5k",
                "explore",
                "explorepage",
                "trending",
                "trendingvideos",
                "easymakeuptutorial",
                "easymakeup",
                "simplemakeup",
                "wintervibes",
                "weddingseason",
                "maybelline",
                "urvashilalwani"
            ],
            "mentions": [
                "plixxo",
                "myglamm"
            ],
            "url": "https://www.instagram.com/p/CYBtWObJJqX/",
            "firstComment": "",
            "latestComments": [],
            "images": [],
            "videoUrl": "https://instagram.fbhk1-3.fna.fbcdn.net/o1/v/t16/f2/m69/AQN19TfTmOtkghIOeQc5YWqInnZUZgPiMMU4djD12QK0pvDyFZb4HSFlm_nswrSmQuDCdnonv4IzvfGL6nX3TVj1.mp4?stp=dst-mp4&efg=eyJxZV9ncm91cHMiOiJbXCJpZ193ZWJfZGVsaXZlcnlfdnRzX290ZlwiXSIsInZlbmNvZGVfdGFnIjoidnRzX3ZvZF91cmxnZW4uaWd0di5jMi43MjAuYmFzZWxpbmUifQ&_nc_cat=104&vs=358968752704400_1435091576&_nc_vs=HBksFQIYOnBhc3N0aHJvdWdoX2V2ZXJzdG9yZS9HR0hER2hBZzN0S2lFRklCQU1CNW9SRE9wd2xiYnZWQkFBQUYVAALIARIAFQIYOnBhc3N0aHJvdWdoX2V2ZXJzdG9yZS9HR3Y5RlJBSkhCN0lxU0VFQU8zQ3p2ZDhtMEFLYnZWQkFBQUYVAgLIARIAKAAYABsBiAd1c2Vfb2lsATEVAAAm9O36qPSLr0AVAigCQzMsF0A%2BszMzMzMzGBJkYXNoX2Jhc2VsaW5lXzFfdjERAHXsB2XCngEA&ccb=9-4&oh=00_AfP5ILv-9lB2mgbWXUeSkyVNsy9Bu5_-ZZldpK9--dYs7A&oe=684B11D7&_nc_sid=8b3546",
            "alt": null,
            "timestamp": "2021-12-28T12:34:41.000Z",
            "childPosts": [],
            "ownerUsername": "_urvashi_lalwani_",
            "ownerId": "32419739756",
            "productType": "igtv",
            "taggedUsers": [
                {
                    "full_name": "#MyGlamm",
                    "id": "1763290204",
                    "is_verified": true,
                    "profile_pic_url": "https://instagram.fbhk1-2.fna.fbcdn.net/v/t51.2885-19/302166708_6402705889746334_6937096037381429548_n.jpg?stp=dst-jpg_e0_s150x150_tt6&_nc_ht=instagram.fbhk1-2.fna.fbcdn.net&_nc_cat=110&_nc_oc=Q6cZ2QHHpibXBwkkYREhypZpew140bZPQbx9vFpJmgGXlquy5XXQR0SASXlUhAxAvHtaiT0&_nc_ohc=AhkpQNjxfTMQ7kNvwFHog4O&_nc_gid=e5mGv2vdFcvv89Ua151bSA&edm=AOQ1c0wBAAAA&ccb=7-5&oh=00_AfPK2e5h0pCThtv5xmc3pVEmF_-nN2MmYSVRxQIiyYjQ9w&oe=684EF1DC&_nc_sid=8b3546",
                    "username": "myglamm"
                }
            ],
            "isCommentsDisabled": false
        },
        {
            "type": "Video",
            "shortCode": "CXLwf4joCWf",
            "title": "",
            "caption": "One brand makeup - @maybelline\n.\n.\n \n#makeup #makeuplook #makeuptherapy #makeuptutorial #easylook #muasunder5k #explore #explorepage #trending #trendingvideos #makeuptutorial #easymakeuptutorial #easymakeup #simplemakeup #wintervibes #weddingseason #maybelline #urvashilalwani",
            "commentsCount": 7,
            "commentsDisabled": false,
            "dimensionsHeight": 995,
            "dimensionsWidth": 640,
            "displayUrl": "https://instagram.fbhk1-2.fna.fbcdn.net/v/t51.29350-15/265269992_1082850959234349_9020721395045262467_n.jpg?stp=dst-jpg_e35_tt6&_nc_ht=instagram.fbhk1-2.fna.fbcdn.net&_nc_cat=109&_nc_oc=Q6cZ2QHHpibXBwkkYREhypZpew140bZPQbx9vFpJmgGXlquy5XXQR0SASXlUhAxAvHtaiT0&_nc_ohc=Al5LsN_8nP0Q7kNvwG6Xall&_nc_gid=e5mGv2vdFcvv89Ua151bSA&edm=AOQ1c0wBAAAA&ccb=7-5&oh=00_AfPG4URfE-wPHIptjBKDysZgUSSLPGge8rPU7vFNN_1xSg&oe=684ED5F0&_nc_sid=8b3546",
            "likesCount": 86,
            "videoDuration": 54.366,
            "videoViewCount": 2862,
            "id": "2723483696939148703",
            "hashtags": [
                "makeup",
                "makeuplook",
                "makeuptherapy",
                "makeuptutorial",
                "easylook",
                "muasunder5k",
                "explore",
                "explorepage",
                "trending",
                "trendingvideos",
                "easymakeuptutorial",
                "easymakeup",
                "simplemakeup",
                "wintervibes",
                "weddingseason",
                "maybelline",
                "urvashilalwani"
            ],
            "mentions": [
                "maybelline"
            ],
            "url": "https://www.instagram.com/p/CXLwf4joCWf/",
            "firstComment": "",
            "latestComments": [],
            "images": [],
            "videoUrl": "https://instagram.fbhk1-2.fna.fbcdn.net/o1/v/t16/f2/m84/AQOOFovBr-nBLK9eiGF6VEu1ApNiHqbslbVVzldz7rnwy9OxTh1xdE7fHcFBduOiDoZzQhRp9GH-lzgDw4fxE83FcrCW1Yvz-0uQn9c.mp4?stp=dst-mp4&efg=eyJxZV9ncm91cHMiOiJbXCJpZ193ZWJfZGVsaXZlcnlfdnRzX290ZlwiXSIsInZlbmNvZGVfdGFnIjoidnRzX3ZvZF91cmxnZW4uaWd0di5jMi43MjAuYmFzZWxpbmUifQ&_nc_cat=110&vs=130083296833911_616865685&_nc_vs=HBksFQIYTGlnX2JhY2tmaWxsX3RpbWVsaW5lX3ZvZC8yQTQ1QjhCNDcxQUY4MEYzNTBFNTc4MUJEQjNGQkFBOF92aWRlb19kYXNoaW5pdC5tcDQVAALIARIAFQIYOnBhc3N0aHJvdWdoX2V2ZXJzdG9yZS9HSU1Nd0JiTzN3a3NuQXdHQUdyNV9GamhJM0JjYnBrd0FBQUYVAgLIARIAKAAYABsBiAd1c2Vfb2lsATEVAAAmyOb18JP9zz8VAigCQzMsF0BLLtkWhysCGBJkYXNoX2Jhc2VsaW5lXzFfdjERAHXsB2XCngEA&ccb=9-4&oh=00_AfMl-5OZXdd8PtFzawYvPNyPFsMI4v0WhM1ZGBb75m4siA&oe=684AF351&_nc_sid=8b3546",
            "alt": null,
            "timestamp": "2021-12-07T13:43:33.000Z",
            "childPosts": [],
            "locationName": "India",
            "locationId": "109524955741121",
            "ownerUsername": "_urvashi_lalwani_",
            "ownerId": "32419739756",
            "productType": "igtv",
            "taggedUsers": [
                {
                    "full_name": "Maybelline New York",
                    "id": "192301204",
                    "is_verified": true,
                    "profile_pic_url": "https://instagram.fbhk1-4.fna.fbcdn.net/v/t51.2885-19/198028759_692833654857282_797261321924659386_n.jpg?stp=dst-jpg_e0_s150x150_tt6&_nc_ht=instagram.fbhk1-4.fna.fbcdn.net&_nc_cat=1&_nc_oc=Q6cZ2QHHpibXBwkkYREhypZpew140bZPQbx9vFpJmgGXlquy5XXQR0SASXlUhAxAvHtaiT0&_nc_ohc=jHQp-UuxJLoQ7kNvwG2TQqM&_nc_gid=e5mGv2vdFcvv89Ua151bSA&edm=AOQ1c0wBAAAA&ccb=7-5&oh=00_AfO2-5pQRI2Zc9os4mxg8nybtYnk53gCQdEQuGSQaSwE6g&oe=684F0AEC&_nc_sid=8b3546",
                    "username": "maybelline"
                },
                {
                    "full_name": "Nykaa",
                    "id": "1239427745",
                    "is_verified": true,
                    "profile_pic_url": "https://instagram.fbhk1-4.fna.fbcdn.net/v/t51.2885-19/492147465_1332830348012991_8786465006454981652_n.jpg?stp=dst-jpg_e0_s150x150_tt6&_nc_ht=instagram.fbhk1-4.fna.fbcdn.net&_nc_cat=1&_nc_oc=Q6cZ2QHHpibXBwkkYREhypZpew140bZPQbx9vFpJmgGXlquy5XXQR0SASXlUhAxAvHtaiT0&_nc_ohc=IRqIG9IvQqQQ7kNvwHAOel_&_nc_gid=e5mGv2vdFcvv89Ua151bSA&edm=AOQ1c0wBAAAA&ccb=7-5&oh=00_AfOa4X3mw_1WalN4c6Pra6klWsG3Zn5oMUqOBcW9c9arlA&oe=684EDC34&_nc_sid=8b3546",
                    "username": "mynykaa"
                }
            ],
            "isCommentsDisabled": false
        },
        {
            "type": "Video",
            "shortCode": "COKLwqOni_0",
            "title": "Summer bridal Makeup.",
            "caption": "Products used- @myglamm Clean beauty Argan oil Bb foundation in oak @myglamm Clean beauty cocoa butter lip n cheek pencil in french rose @myglamm HD duo highlighter champagne/ rose gold @myglamm Stay defined liquid eyeliner+HD brow powder @myglamm Perfect curves moisturising matte lip cream- 010 Passion . Head to my bio to take the great glamm survey and get a free lipstick. #MyGlammXO #MyGlammXOBeautyCreator @myglammxo_beautycreator @plixxo @popxobeauty @myglamm #igtv #makeup",
            "commentsCount": 20,
            "commentsDisabled": false,
            "dimensionsHeight": 995,
            "dimensionsWidth": 640,
            "displayUrl": "https://instagram.fbhk1-1.fna.fbcdn.net/v/t51.29350-15/177690640_904540596994463_8697774066958601637_n.jpg?stp=dst-jpg_e35_tt6&_nc_ht=instagram.fbhk1-1.fna.fbcdn.net&_nc_cat=111&_nc_oc=Q6cZ2QHHpibXBwkkYREhypZpew140bZPQbx9vFpJmgGXlquy5XXQR0SASXlUhAxAvHtaiT0&_nc_ohc=bCnDJUUezN0Q7kNvwF_nhG1&_nc_gid=e5mGv2vdFcvv89Ua151bSA&edm=AOQ1c0wBAAAA&ccb=7-5&oh=00_AfPGxzFrkA15DcU-IYyKGbkFs2MRtKGiAF3ykvW9vUvzNA&oe=684ED734&_nc_sid=8b3546",
            "likesCount": 56,
            "videoDuration": 88.833,
            "videoViewCount": 166,
            "id": "2560911060502458356",
            "hashtags": [
                "MyGlammXO",
                "MyGlammXOBeautyCreator",
                "igtv",
                "makeup"
            ],
            "mentions": [
                "myglamm",
                "myglammxo_beautycreator",
                "plixxo",
                "popxobeauty"
            ],
            "url": "https://www.instagram.com/p/COKLwqOni_0/",
            "firstComment": "",
            "latestComments": [],
            "images": [],
            "videoUrl": "https://instagram.fbhk1-4.fna.fbcdn.net/o1/v/t16/f2/m84/AQOErAmN6ThTlAoo1vl3EsYJvMK9nHCpM1FHJPi5avziGKPaTnHvN9zVyo9S3ZNc3HnWFqfPUP9Mp5fmF_2YnrhDJrVFMsarhh92Wjw.mp4?stp=dst-mp4&efg=eyJxZV9ncm91cHMiOiJbXCJpZ193ZWJfZGVsaXZlcnlfdnRzX290ZlwiXSIsInZlbmNvZGVfdGFnIjoidnRzX3ZvZF91cmxnZW4uaWd0di5jMi43MjAuYmFzZWxpbmUifQ&_nc_cat=108&vs=173789839127440_662230403&_nc_vs=HBksFQIYTGlnX2JhY2tmaWxsX3RpbWVsaW5lX3ZvZC83RDQ3Q0M5ODAzQTA1OTY3OTFDQjQ0MkQwN0YyRjQ5NV92aWRlb19kYXNoaW5pdC5tcDQVAALIARIAFQIYOnBhc3N0aHJvdWdoX2V2ZXJzdG9yZS9HRXRpamhmWWFOcUJpWXdDQUY2TVVwUEl2Y3hjYnBrd0FBQUYVAgLIARIAKAAYABsBiAd1c2Vfb2lsATEVAAAmrviTkvjx1D8VAigCQzMsF0BWNU%2FfO2RaGBJkYXNoX2Jhc2VsaW5lXzFfdjERAHXsB2XCngEA&ccb=9-4&oh=00_AfOhU_oEoMjqsq6PnkfY6GMnk3jPF2peYi5ZbQxMZ4afPQ&oe=684B0E34&_nc_sid=8b3546",
            "alt": null,
            "timestamp": "2021-04-27T06:20:54.000Z",
            "childPosts": [],
            "ownerUsername": "_urvashi_lalwani_",
            "ownerId": "32419739756",
            "productType": "igtv",
            "isCommentsDisabled": false
        },
        {
            "type": "Video",
            "shortCode": "CN6uW7Pnr1G",
            "title": "EASY KOHL EYES",
            "caption": "@mamaearth.in oil free face moisturizer\n@maybelline.india Fit me  Foundation - Warm nude 128\n@nyxcosmetics_in liquid illuminator- Sunbeam\n@swissbeautycosmetics\nconcealer -02\n@lakmeindia eyeconic kajal- Black\n@maybelline.india Mascara\n@nyxcosmetics_in Setting spray- Matte \n@myglamm Lip and cheek tint- French rose\n@myglamm Ultimate long stay matte lipstick- 07 Goddess\n.\n.\n.\n#makeup #kohleyes #lakmeindia #makeupinfluencer #makeuptutorial #indianmakeup #MyGlamm #nykaacosmetics #nykaa #maybellineindia #nagpurblogger  #makeuptransformation #makeupoftheday #looks #\u2764\ufe0f\u2764\ufe0f\u2764\ufe0f\u2764\ufe0f\u2764\ufe0f\u2764\ufe0f",
            "commentsCount": 34,
            "commentsDisabled": false,
            "dimensionsHeight": 995,
            "dimensionsWidth": 640,
            "displayUrl": "https://instagram.fbhk1-2.fna.fbcdn.net/v/t51.29350-15/176289844_163156865708601_838401284889136957_n.jpg?stp=dst-jpg_e35_tt6&_nc_ht=instagram.fbhk1-2.fna.fbcdn.net&_nc_cat=109&_nc_oc=Q6cZ2QHHpibXBwkkYREhypZpew140bZPQbx9vFpJmgGXlquy5XXQR0SASXlUhAxAvHtaiT0&_nc_ohc=va4AJFGePaMQ7kNvwEmF4fk&_nc_gid=e5mGv2vdFcvv89Ua151bSA&edm=AOQ1c0wBAAAA&ccb=7-5&oh=00_AfNIDmW87gOA38-v71AuEAbMr3liZRxbCAlpvoK_y65AoQ&oe=684EFDEC&_nc_sid=8b3546",
            "likesCount": 72,
            "videoDuration": 130.366,
            "videoViewCount": 418,
            "id": "2556559624067005766",
            "hashtags": [
                "makeup",
                "kohleyes",
                "lakmeindia",
                "makeupinfluencer",
                "makeuptutorial",
                "indianmakeup",
                "MyGlamm",
                "nykaacosmetics",
                "nykaa",
                "maybellineindia",
                "nagpurblogger",
                "makeuptransformation",
                "makeupoftheday",
                "looks",
                "\u2764\ufe0f\u2764\ufe0f\u2764\ufe0f\u2764\ufe0f\u2764\ufe0f\u2764\ufe0f"
            ],
            "mentions": [
                "mamaearth.in",
                "maybelline.india",
                "nyxcosmetics_in",
                "swissbeautycosmetics",
                "lakmeindia",
                "myglamm"
            ],
            "url": "https://www.instagram.com/p/CN6uW7Pnr1G/",
            "firstComment": "",
            "latestComments": [],
            "images": [],
            "videoUrl": "https://instagram.fbhk1-3.fna.fbcdn.net/o1/v/t16/f2/m84/AQOwGvKtd_vTJbijuCI5en4tjyOuMniwUui8X02NKvDcAG0pTuY7JOUPLg9k-e5jxF97gdUOGvJ0Gphg4rbKlWXf39J0-B3Xd3ayrlw.mp4?stp=dst-mp4&efg=eyJxZV9ncm91cHMiOiJbXCJpZ193ZWJfZGVsaXZlcnlfdnRzX290ZlwiXSIsInZlbmNvZGVfdGFnIjoidnRzX3ZvZF91cmxnZW4uaWd0di5jMi43MjAuYmFzZWxpbmUifQ&_nc_cat=103&vs=856533262691814_3551242130&_nc_vs=HBksFQIYTGlnX2JhY2tmaWxsX3RpbWVsaW5lX3ZvZC8zRTQ1QzFEQjQ1MDc0MTQ1NjBFOTY3NEZDMEE3MjRCMV92aWRlb19kYXNoaW5pdC5tcDQVAALIARIAFQIYOnBhc3N0aHJvdWdoX2V2ZXJzdG9yZS9HTzBBWlJlZWhfUW9UWHNDQUZJZlZvV2VxczFVYnBrd0FBQUYVAgLIARIAKAAYABsBiAd1c2Vfb2lsATEVAAAm%2BMyhgvDPzT8VAigCQzMsF0BgS7ZFocrBGBJkYXNoX2Jhc2VsaW5lXzFfdjERAHXsB2XCngEA&ccb=9-4&oh=00_AfNx8R_ctl7_6fEuR0LPonR6M1KCj0dYC5nGakjvxi3ZCw&oe=684B0F10&_nc_sid=8b3546",
            "alt": null,
            "timestamp": "2021-04-21T06:15:17.000Z",
            "childPosts": [],
            "ownerUsername": "_urvashi_lalwani_",
            "ownerId": "32419739756",
            "productType": "igtv",
            "isCommentsDisabled": false
        },
        {
            "type": "Video",
            "shortCode": "CNt4vwOH7un",
            "title": "Red and golden eye makeup \u2764\ufe0f\u2728",
            "caption": "Products used- \n@pondsindia Super light gel\n@swissbeautycosmetics concealer 02\n@lagirlindia pro concealer Pure beige\n@paccosmetic foundation brush 265\n@myglamm lip and cheek tint - French rose\n@maybelline.india Hyper curl mascara\n@nyxcosmetics_in Born to glow liquid illuminator (LI01 sunbeam)\n@makeuprevolutionindia eyeshadow palette Marvellous mattes\n@nykaabeauty eyeshadow blending brush\n@trysugar lipstick\n.\n.\n.\n.\n.\n#makeup #trysugar #trysugarcosmetics #nykaacosmetics #mynykaabeauty #makeuplooks #tutorial #redeyes #makeuprevolution #nagpurbloggers #makeupoftheday #indianmakeup #traditionmakeup #maybellineindia #paccosmeticsindia #swissbeauty #lagirlcosmetics #MyGlammXOBeautyCreator #MyGlamm #nyxcosmetics #pondsindia #summermakeup",
            "commentsCount": 10,
            "commentsDisabled": false,
            "dimensionsHeight": 995,
            "dimensionsWidth": 640,
            "displayUrl": "https://instagram.fbhk1-4.fna.fbcdn.net/v/t51.29350-15/173417826_1061933544330746_3240433860214800936_n.jpg?stp=dst-jpg_e35_tt6&_nc_ht=instagram.fbhk1-4.fna.fbcdn.net&_nc_cat=102&_nc_oc=Q6cZ2QHHpibXBwkkYREhypZpew140bZPQbx9vFpJmgGXlquy5XXQR0SASXlUhAxAvHtaiT0&_nc_ohc=yXLhsfxqV4gQ7kNvwEQgLYw&_nc_gid=e5mGv2vdFcvv89Ua151bSA&edm=AOQ1c0wBAAAA&ccb=7-5&oh=00_AfP2dOe1m3eBbPNcPojqV9A5aknpR9LlqHW1_-M19VUeMA&oe=684EECC1&_nc_sid=8b3546",
            "likesCount": 57,
            "videoDuration": 91.233,
            "videoViewCount": 273,
            "id": "2552946135985535911",
            "hashtags": [
                "makeup",
                "trysugar",
                "trysugarcosmetics",
                "nykaacosmetics",
                "mynykaabeauty",
                "makeuplooks",
                "tutorial",
                "redeyes",
                "makeuprevolution",
                "nagpurbloggers",
                "makeupoftheday",
                "indianmakeup",
                "traditionmakeup",
                "maybellineindia",
                "paccosmeticsindia",
                "swissbeauty",
                "lagirlcosmetics",
                "MyGlammXOBeautyCreator",
                "MyGlamm",
                "nyxcosmetics",
                "pondsindia",
                "summermakeup"
            ],
            "mentions": [
                "pondsindia",
                "swissbeautycosmetics",
                "lagirlindia",
                "paccosmetic",
                "myglamm",
                "maybelline.india",
                "nyxcosmetics_in",
                "makeuprevolutionindia",
                "nykaabeauty",
                "trysugar"
            ],
            "url": "https://www.instagram.com/p/CNt4vwOH7un/",
            "firstComment": "",
            "latestComments": [],
            "images": [],
            "videoUrl": "https://instagram.fbhk1-4.fna.fbcdn.net/o1/v/t16/f2/m84/AQOadN2gP7tNjwjyRgOZKq2I9zVzx2u-sJowztzu7lKBG887Z-q2ONyC62l6GBN7bpfd60y1MycJjJ7TW6BVSg94fuxalBPh12p9Nv8.mp4?stp=dst-mp4&efg=eyJxZV9ncm91cHMiOiJbXCJpZ193ZWJfZGVsaXZlcnlfdnRzX290ZlwiXSIsInZlbmNvZGVfdGFnIjoidnRzX3ZvZF91cmxnZW4uaWd0di5jMi43MjAuYmFzZWxpbmUifQ&_nc_cat=108&vs=224516633970004_3528738892&_nc_vs=HBksFQIYTGlnX2JhY2tmaWxsX3RpbWVsaW5lX3ZvZC9BMjQ4OUYzMjY2MEJDRDcwNTAyOEYyQTdGQThCODlCM192aWRlb19kYXNoaW5pdC5tcDQVAALIARIAFQIYOnBhc3N0aHJvdWdoX2V2ZXJzdG9yZS9HQ0R1TWhjZTRxekVOd3dEQVBSV3ZUSHFOLU1DYnBrd0FBQUYVAgLIARIAKAAYABsBiAd1c2Vfb2lsATEVAAAmiM%2BuqbC8yz8VAigCQzMsF0BWzul41P30GBJkYXNoX2Jhc2VsaW5lXzFfdjERAHXsB2XCngEA&ccb=9-4&oh=00_AfOrM5R5_1B_Gc6fRqQkeLESQ6f7fTVFatCI2iv4fmFRDQ&oe=684B05E8&_nc_sid=8b3546",
            "alt": null,
            "timestamp": "2021-04-16T06:35:46.000Z",
            "childPosts": [],
            "ownerUsername": "_urvashi_lalwani_",
            "ownerId": "32419739756",
            "productType": "igtv",
            "isCommentsDisabled": false
        },
        {
            "type": "Video",
            "shortCode": "CNZUfdYnVXZ",
            "title": "Wearable Blue Eyes\ud83d\udc99",
            "caption": "Products used- \n@pondsindia Super light gel\n@stayquirky.in Primer\n@maybelline.india Fit me foundation in shade warm nude 128\n@lagirlindia pro concealer \n@paccosmetic foundation brush 265\n@nyxcosmetics_in Born to glow liquid illuminator (LI01 sunbeam)\n@makeuprevolutionindia eyeshadow palette Marvellous mattes\n@nykaabeauty eyeshadow blending brush\n@lakmeindia Insta eyeliner- blue\n@mynykaa Liquid lipstick - Bombae\n.\n.\n.\n.\n.\n.\n#makeup #makeupreels #makeuplovers #makeuplooks #makeupinfluencer #makeuptutorial #blueeyeshadow #blue #makeupoftheday #lakme #lakmeindia #maybellineindia #nyxcosmetics #paccosmeticsindia #lagirlcosmetics #mynykaabeauty #mynykaa #pondsindia #stayquirky #indianmakeup #blueyes\ud83d\udc99 #\ud83d\udc99\ud83d\udc99 #\ud83d\udc99\ud83d\udc99\ud83d\udc99\ud83d\udc99\ud83d\udc99\ud83d\udc99\ud83d\udc99\ud83d\udc99\ud83d\udc99\ud83d\udc99\ud83d\udc99\ud83d\udc99\ud83d\udc99\ud83d\udc99\ud83d\udc99\ud83d\udc99\ud83d\udc99\ud83d\udc99\ud83d\udc99\ud83d\udc99\ud83d\udc99\ud83d\udc99\ud83d\udc99\ud83d\udc99\ud83d\udc99\ud83d\udc99\ud83d\udc99\ud83d\udc99\ud83d\udc99\ud83d\udc99\ud83d\udc99\ud83d\udc99\ud83d\udc99\ud83d\udc99\ud83d\udc99\ud83d\udc99\ud83d\udc99\ud83d\udc99\ud83d\udc99\ud83d\udc99\ud83d\udc99\ud83d\udc99\ud83d\udc99\ud83d\udc99\ud83d\udc99\ud83d\udc99\ud83d\udc99\ud83d\udc99\ud83d\udc99\ud83d\udc99\ud83d\udc99\ud83d\udc99\ud83d\udc99\ud83d\udc99\ud83d\udc99\ud83d\udc99\ud83d\udc99\ud83d\udc99\ud83d\udc99\ud83d\udc99\ud83d\udc99\ud83d\udc99\ud83d\udc99\ud83d\udc99\ud83d\udc99\ud83d\udc99\ud83d\udc99\ud83d\udc99\ud83d\udc99",
            "commentsCount": 20,
            "commentsDisabled": false,
            "dimensionsHeight": 995,
            "dimensionsWidth": 640,
            "displayUrl": "https://instagram.fbhk1-4.fna.fbcdn.net/v/t51.29350-15/169266215_116699953785206_2071662070412969926_n.jpg?stp=dst-jpg_e35_tt6&_nc_ht=instagram.fbhk1-4.fna.fbcdn.net&_nc_cat=102&_nc_oc=Q6cZ2QHHpibXBwkkYREhypZpew140bZPQbx9vFpJmgGXlquy5XXQR0SASXlUhAxAvHtaiT0&_nc_ohc=smHX4gqXeUgQ7kNvwF5pzRd&_nc_gid=e5mGv2vdFcvv89Ua151bSA&edm=AOQ1c0wBAAAA&ccb=7-5&oh=00_AfNmEZ4iFXITyO2GQqsONoxbHA334wzZpxrZoUfs8QvSvA&oe=684F083E&_nc_sid=8b3546",
            "likesCount": 67,
            "videoDuration": 81.1,
            "videoViewCount": 258,
            "id": "2547157187040204249",
            "hashtags": [
                "makeup",
                "makeupreels",
                "makeuplovers",
                "makeuplooks",
                "makeupinfluencer",
                "makeuptutorial",
                "blueeyeshadow",
                "blue",
                "makeupoftheday",
                "lakme",
                "lakmeindia",
                "maybellineindia",
                "nyxcosmetics",
                "paccosmeticsindia",
                "lagirlcosmetics",
                "mynykaabeauty",
                "mynykaa",
                "pondsindia",
                "stayquirky",
                "indianmakeup",
                "blueyes\ud83d\udc99",
                "\ud83d\udc99\ud83d\udc99",
                "\ud83d\udc99\ud83d\udc99\ud83d\udc99\ud83d\udc99\ud83d\udc99\ud83d\udc99\ud83d\udc99\ud83d\udc99\ud83d\udc99\ud83d\udc99\ud83d\udc99\ud83d\udc99\ud83d\udc99\ud83d\udc99\ud83d\udc99\ud83d\udc99\ud83d\udc99\ud83d\udc99\ud83d\udc99\ud83d\udc99\ud83d\udc99\ud83d\udc99\ud83d\udc99\ud83d\udc99\ud83d\udc99\ud83d\udc99\ud83d\udc99\ud83d\udc99\ud83d\udc99\ud83d\udc99\ud83d\udc99\ud83d\udc99\ud83d\udc99\ud83d\udc99\ud83d\udc99\ud83d\udc99\ud83d\udc99\ud83d\udc99\ud83d\udc99\ud83d\udc99\ud83d\udc99\ud83d\udc99\ud83d\udc99\ud83d\udc99\ud83d\udc99\ud83d\udc99\ud83d\udc99\ud83d\udc99\ud83d\udc99\ud83d\udc99\ud83d\udc99\ud83d\udc99\ud83d\udc99\ud83d\udc99\ud83d\udc99\ud83d\udc99\ud83d\udc99\ud83d\udc99\ud83d\udc99\ud83d\udc99\ud83d\udc99\ud83d\udc99\ud83d\udc99\ud83d\udc99\ud83d\udc99\ud83d\udc99\ud83d\udc99\ud83d\udc99\ud83d\udc99"
            ],
            "mentions": [
                "pondsindia",
                "stayquirky.in",
                "maybelline.india",
                "lagirlindia",
                "paccosmetic",
                "nyxcosmetics_in",
                "makeuprevolutionindia",
                "nykaabeauty",
                "lakmeindia",
                "mynykaa"
            ],
            "url": "https://www.instagram.com/p/CNZUfdYnVXZ/",
            "firstComment": "",
            "latestComments": [],
            "images": [],
            "videoUrl": "https://instagram.fbhk1-1.fna.fbcdn.net/o1/v/t16/f2/m84/AQPnxQ0D0tPuQI_fokYc7oOV-Nal0VXFsaJkz8RUloOWUdGXUHdNgsA5ZN9cDLP3UnMDRWVzI1FYzmX0FG4-eLtaB4QWo4SErFtFH_Q.mp4?stp=dst-mp4&efg=eyJxZV9ncm91cHMiOiJbXCJpZ193ZWJfZGVsaXZlcnlfdnRzX290ZlwiXSIsInZlbmNvZGVfdGFnIjoidnRzX3ZvZF91cmxnZW4uaWd0di5jMi43MjAuYmFzZWxpbmUifQ&_nc_cat=111&vs=349325604323628_4052672507&_nc_vs=HBksFQIYTGlnX2JhY2tmaWxsX3RpbWVsaW5lX3ZvZC9CRDQyQUM3RjE0MkQ4MkZCRTdEMEUxNUI0NjlEQUI4RV92aWRlb19kYXNoaW5pdC5tcDQVAALIARIAFQIYOnBhc3N0aHJvdWdoX2V2ZXJzdG9yZS9HTUhZZXhlcHBWR01MdkFEQU1NNDEzRElXMk5ZYnBrd0FBQUYVAgLIARIAKAAYABsBiAd1c2Vfb2lsATEVAAAm7LaM3Kv0zz8VAigCQzMsF0BURmZmZmZmGBJkYXNoX2Jhc2VsaW5lXzFfdjERAHXsB2XCngEA&ccb=9-4&oh=00_AfPAnfEXds2KDC4l8U-f40o_o4nUEtCAMZQhx6uJH-VIlw&oe=684B0881&_nc_sid=8b3546",
            "alt": null,
            "timestamp": "2021-04-08T06:54:10.000Z",
            "childPosts": [],
            "ownerUsername": "_urvashi_lalwani_",
            "ownerId": "32419739756",
            "productType": "igtv",
            "isCommentsDisabled": false
        },
        {
            "type": "Video",
            "shortCode": "CM4cQzCHDYt",
            "title": "\u2728SUBTLE DEWY MAKEUP LOOK FOR COLLEGE \u2728",
            "caption": "products used-\n@pondsindia super light gel moisturizer\n@maybelline.india fit me in the shade 128 warm nude\n@nyxcosmetics_in Born to glow liquid illuminator - Sunbeam\n@swissbeautycosmetics concealer - 02\n@lakmeindia Eyekonic kajal - black\n@maybelline.india mascara\n@myglamm cocoa butter lip and cheeck pencil- French rose\n@myglamm pose HD highlighter duo champagne/ rose gold\n@mynykaa Lipstick in the shade - Bombae\n.\n.\n.\n.\n.\n.\n#makeup #collegemakeup #dewymakeuplook #subtlemakeup #makeuplovers #summermakeup #makeuptutorial #makeupaddict #dewymakeup #foundation #concealer #maybellineindia #lakme #nykaa #nyxcosmetics  #MyGlamm \n#swissbeauty #ponds #pondsindia #nagpur #mumbai #pune #india #pinkmakeup #everydaylook",
            "commentsCount": 22,
            "commentsDisabled": false,
            "dimensionsHeight": 995,
            "dimensionsWidth": 640,
            "displayUrl": "https://instagram.fbhk1-4.fna.fbcdn.net/v/t51.29350-15/164937576_720566858616656_3951793923436198972_n.jpg?stp=dst-jpg_e35_tt6&_nc_ht=instagram.fbhk1-4.fna.fbcdn.net&_nc_cat=108&_nc_oc=Q6cZ2QHHpibXBwkkYREhypZpew140bZPQbx9vFpJmgGXlquy5XXQR0SASXlUhAxAvHtaiT0&_nc_ohc=LeWqTIw2GeAQ7kNvwHFOy55&_nc_gid=e5mGv2vdFcvv89Ua151bSA&edm=AOQ1c0wBAAAA&ccb=7-5&oh=00_AfPYPlA_lh3g4_GcoqIDsTqcbAqU870OyEJ-9YKoHKOGbQ&oe=684EE2D3&_nc_sid=8b3546",
            "likesCount": 70,
            "videoDuration": 134.033,
            "videoViewCount": 273,
            "id": "2537902689633449517",
            "hashtags": [
                "makeup",
                "collegemakeup",
                "dewymakeuplook",
                "subtlemakeup",
                "makeuplovers",
                "summermakeup",
                "makeuptutorial",
                "makeupaddict",
                "dewymakeup",
                "foundation",
                "concealer",
                "maybellineindia",
                "lakme",
                "nykaa",
                "nyxcosmetics",
                "MyGlamm",
                "swissbeauty",
                "ponds",
                "pondsindia",
                "nagpur",
                "mumbai",
                "pune",
                "india",
                "pinkmakeup",
                "everydaylook"
            ],
            "mentions": [
                "pondsindia",
                "maybelline.india",
                "nyxcosmetics_in",
                "swissbeautycosmetics",
                "lakmeindia",
                "myglamm",
                "mynykaa"
            ],
            "url": "https://www.instagram.com/p/CM4cQzCHDYt/",
            "firstComment": "",
            "latestComments": [],
            "images": [],
            "videoUrl": "https://instagram.fbhk1-3.fna.fbcdn.net/o1/v/t16/f2/m84/AQNNRhwx-PoO2Q15ayrckqYDenJrw9o61-QDaxKK1r7KWSfoSnxmx3tVI6eHFd1q54utzv7XDve66h1WBnD5oK7K0LXLsrGv6_DeqfI.mp4?stp=dst-mp4&efg=eyJxZV9ncm91cHMiOiJbXCJpZ193ZWJfZGVsaXZlcnlfdnRzX290ZlwiXSIsInZlbmNvZGVfdGFnIjoidnRzX3ZvZF91cmxnZW4uaWd0di5jMi43MjAuYmFzZWxpbmUifQ&_nc_cat=104&vs=882403610094512_2088835057&_nc_vs=HBksFQIYTGlnX2JhY2tmaWxsX3RpbWVsaW5lX3ZvZC8wRjRFODk3QzlFQTU0RTMyOTA3RUFFM0Q4NUYzMkM5Nl92aWRlb19kYXNoaW5pdC5tcDQVAALIARIAFQIYOnBhc3N0aHJvdWdoX2V2ZXJzdG9yZS9HRXZRbUJZbXhtTXpaa1FhQU5fVURDVS1OMUZUYnBrd0FBQUYVAgLIARIAKAAYABsBiAd1c2Vfb2lsATEVAAAmgpiRh%2BD80T8VAigCQzMsF0BgwQ5WBBiTGBJkYXNoX2Jhc2VsaW5lXzFfdjERAHXsB2XCngEA&ccb=9-4&oh=00_AfOp4y2wNNqWJ4eO-GbLmUFYitUOIgm690tD_NwZOslkqA&oe=684AF0DC&_nc_sid=8b3546",
            "alt": null,
            "timestamp": "2021-03-26T12:27:21.000Z",
            "childPosts": [],
            "ownerUsername": "_urvashi_lalwani_",
            "ownerId": "32419739756",
            "productType": "igtv",
            "isCommentsDisabled": false
        },
        {
            "type": "Video",
            "shortCode": "CJBlFIlHzi8",
            "title": "So the wait is over\u263a\ufe0f NYKAA HAUL @mynykaa @nykaabeauty",
            "caption": ".\n.\n.\n.\n.\n.\n.\n.\n.\n#makeup #hauls #haul #makeuhaul #nykaahaul #beauty #sale #trendingsongs #trending #viral #igtv #beautyblogger #urvashilalwani #beautiful #shopping #shoppingonline #nykaa #nykaacosmetics #nykaabeauty #nykaapinkfridaysale #nykaaluxe #nykaaexclusive #nykaasale #nagpur #nagpurblogger #indianblogger",
            "commentsCount": 12,
            "commentsDisabled": false,
            "dimensionsHeight": 995,
            "dimensionsWidth": 640,
            "displayUrl": "https://instagram.fbhk1-2.fna.fbcdn.net/v/t51.29350-15/131890488_1332399113793425_4196393033842921501_n.jpg?stp=dst-jpg_e35_tt6&_nc_ht=instagram.fbhk1-2.fna.fbcdn.net&_nc_cat=105&_nc_oc=Q6cZ2QHHpibXBwkkYREhypZpew140bZPQbx9vFpJmgGXlquy5XXQR0SASXlUhAxAvHtaiT0&_nc_ohc=X7WEZ7SWuw8Q7kNvwE6E9PQ&_nc_gid=e5mGv2vdFcvv89Ua151bSA&edm=AOQ1c0wBAAAA&ccb=7-5&oh=00_AfOyfbRv6onSpeVkMkiWUW2-0x6DWPwWg56FPk6x6tQPUg&oe=684EF014&_nc_sid=8b3546",
            "likesCount": 82,
            "videoDuration": 372.266,
            "videoViewCount": 311,
            "id": "2468417151306774716",
            "hashtags": [
                "makeup",
                "hauls",
                "haul",
                "makeuhaul",
                "nykaahaul",
                "beauty",
                "sale",
                "trendingsongs",
                "trending",
                "viral",
                "igtv",
                "beautyblogger",
                "urvashilalwani",
                "beautiful",
                "shopping",
                "shoppingonline",
                "nykaa",
                "nykaacosmetics",
                "nykaabeauty",
                "nykaapinkfridaysale",
                "nykaaluxe",
                "nykaaexclusive",
                "nykaasale",
                "nagpur",
                "nagpurblogger",
                "indianblogger"
            ],
            "mentions": [],
            "url": "https://www.instagram.com/p/CJBlFIlHzi8/",
            "firstComment": "",
            "latestComments": [],
            "images": [],
            "videoUrl": "https://instagram.fbhk1-3.fna.fbcdn.net/o1/v/t16/f2/m84/AQNJOqKvHb2bOOemAa_PmRdO4VbjXfeJs5E70Ni-rYh4cdtHPiQcYS3pd9_Sw3yg3sVx35OjbV-z68fL5ziDAFBCbXHieWZC1uvPY-E.mp4?stp=dst-mp4&efg=eyJxZV9ncm91cHMiOiJbXCJpZ193ZWJfZGVsaXZlcnlfdnRzX290ZlwiXSIsInZlbmNvZGVfdGFnIjoidnRzX3ZvZF91cmxnZW4uaWd0di5jMi43MjAuYmFzZWxpbmUifQ&_nc_cat=100&vs=348569430943672_1635763383&_nc_vs=HBksFQIYTGlnX2JhY2tmaWxsX3RpbWVsaW5lX3ZvZC83RTRCQzZGRTMxQTc0NkE2REQwMkRBQ0JBQkY5MkVBMl92aWRlb19kYXNoaW5pdC5tcDQVAALIARIAFQIYOnBhc3N0aHJvdWdoX2V2ZXJzdG9yZS9HRWNZTWhmTmQ2QjQ3RXNGQU9iMW02Zmk5Mjh4YnBrd0FBQUYVAgLIARIAKAAYABsBiAd1c2Vfb2lsATEVAAAm9vTczoSqwD8VAigCQzMsF0B3REGJN0vHGBJkYXNoX2Jhc2VsaW5lXzFfdjERAHXsB2XCngEA&ccb=9-4&oh=00_AfMxnrVFxRYVMKTDM_iNkO4xPBRr0xZODKEYUCNg074RUQ&oe=684B0E83&_nc_sid=8b3546",
            "alt": null,
            "timestamp": "2020-12-20T15:32:55.000Z",
            "childPosts": [],
            "ownerUsername": "_urvashi_lalwani_",
            "ownerId": "32419739756",
            "productType": "igtv",
            "isCommentsDisabled": false
        },
        {
            "type": "Video",
            "shortCode": "CGRiYaEl4h5",
            "title": "Eye Look 1 (Black and glitter)\ud83d\udc93\ud83d\udc93",
            "caption": "Eyeshadow- @swissbeautycosmetics \nMascara- @maybelline \nLip gloss- @lakmeindia \nHighlighter - @stayquirky.in \nFoundation- @givenchybeauty \nConcealer- @swissbeautycosmetics \n.\n.\n.\n.\n.\n.\n.\n.\n.\n.\n.\n.\n.\n.\n.\n.\n.\n.\n#instantinfluencer #nykaabeautybook #reels #gainpartyb#softgirlaesthetic #tiktokmakeup #egirlaesthetic #muaunder10k #makeup2020 #mmlashes #makeuptiktok #muadiscover #cutcreaselook #testandtell #firemakeup #brownskingirl #brownskinmakeup #gainfollowers #gainfollowersquick #lipglosslover #lipglosslovers #magneticlashes",
            "commentsCount": 56,
            "commentsDisabled": false,
            "dimensionsHeight": 995,
            "dimensionsWidth": 640,
            "displayUrl": "https://instagram.fbhk1-2.fna.fbcdn.net/v/t51.29350-15/121249021_2746433185627242_4956809601060605486_n.jpg?stp=dst-jpg_e35_tt6&_nc_ht=instagram.fbhk1-2.fna.fbcdn.net&_nc_cat=106&_nc_oc=Q6cZ2QHHpibXBwkkYREhypZpew140bZPQbx9vFpJmgGXlquy5XXQR0SASXlUhAxAvHtaiT0&_nc_ohc=MlIG9zLDDT4Q7kNvwH4HlQn&_nc_gid=e5mGv2vdFcvv89Ua151bSA&edm=AOQ1c0wBAAAA&ccb=7-5&oh=00_AfNSq_kPVIz1Nr5afHeKKLyubw8mMkjNzHa4vBy5dPkS9w&oe=684EE137&_nc_sid=8b3546",
            "likesCount": 95,
            "videoDuration": 143.366,
            "videoViewCount": 232,
            "id": "2418865685717813369",
            "hashtags": [
                "instantinfluencer",
                "nykaabeautybook",
                "reels",
                "gainpartyb",
                "softgirlaesthetic",
                "tiktokmakeup",
                "egirlaesthetic",
                "muaunder10k",
                "makeup2020",
                "mmlashes",
                "makeuptiktok",
                "muadiscover",
                "cutcreaselook",
                "testandtell",
                "firemakeup",
                "brownskingirl",
                "brownskinmakeup",
                "gainfollowers",
                "gainfollowersquick",
                "lipglosslover",
                "lipglosslovers",
                "magneticlashes"
            ],
            "mentions": [
                "swissbeautycosmetics",
                "maybelline",
                "lakmeindia",
                "stayquirky.in",
                "givenchybeauty"
            ],
            "url": "https://www.instagram.com/p/CGRiYaEl4h5/",
            "firstComment": "",
            "latestComments": [],
            "images": [],
            "videoUrl": "https://instagram.fbhk1-3.fna.fbcdn.net/o1/v/t16/f2/m84/AQP_Mc4hek7ehptK_qFaleW9r2s7iPPWqEFBZyoV0dc7JDyOUcRqETyLmyj2StP75ElIyflZll-MIkqaLRtKhKHjTgZGaicR8p13fq8.mp4?stp=dst-mp4&efg=eyJxZV9ncm91cHMiOiJbXCJpZ193ZWJfZGVsaXZlcnlfdnRzX290ZlwiXSIsInZlbmNvZGVfdGFnIjoidnRzX3ZvZF91cmxnZW4uaWd0di5jMi43MjAuYmFzZWxpbmUifQ&_nc_cat=100&vs=193699583759074_2553267188&_nc_vs=HBksFQIYTGlnX2JhY2tmaWxsX3RpbWVsaW5lX3ZvZC9EMzQxMjY4MTk1MkIzOTlBMDAzOTZGMzk5OUJDQ0ZCN192aWRlb19kYXNoaW5pdC5tcDQVAALIARIAFQIYOnBhc3N0aHJvdWdoX2V2ZXJzdG9yZS9HSm9JTWhlamFERGo1WVFDQUtIVjZ2enJkSDBhYnBrd0FBQUYVAgLIARIAKAAYABsBiAd1c2Vfb2lsATEVAAAmzp%2FUmpS3vz8VAigCQzMsF0Bh67ZFocrBGBJkYXNoX2Jhc2VsaW5lXzFfdjERAHXsB2XCngEA&ccb=9-4&oh=00_AfPpVRyr6Z61PwfaC6LB9jtkzSxJzlR3rU3ncM20Qv_wuA&oe=684AEDF6&_nc_sid=8b3546",
            "alt": null,
            "timestamp": "2020-10-13T06:42:07.000Z",
            "childPosts": [],
            "ownerUsername": "_urvashi_lalwani_",
            "ownerId": "32419739756",
            "productType": "igtv",
            "isCommentsDisabled": false
        },
        {
            "type": "Video",
            "shortCode": "CF9Inm_lnZu",
            "title": "\u2665\ufe0f\u2665\ufe0fAcne remedy\u2764\ufe0f\u2764\ufe0f NEEM FACE PACK.",
            "caption": "You can add some drops of rose water to make it more Hydrating. \nKeep it on for 10 mins and wash it with normal water. \n.\n.\n.\n.\n.\n\n.\n.\n.\n.\n.\n.\n\n#followforfollowbacks #followersreal #fff\ud83d\udc8b #fff #nagpur #nagpurblogger #nagpurfashion #acneskin #acneproneskincare #acnescars #mumbaiblogger #jaipurblogger #lakme #trysugar #pr #collaboration #collab #neem #facepack #facepackselfie #facepacks #mondaymood",
            "commentsCount": 48,
            "commentsDisabled": false,
            "dimensionsHeight": 995,
            "dimensionsWidth": 640,
            "displayUrl": "https://instagram.fbhk1-4.fna.fbcdn.net/v/t51.29350-15/120832002_100404005165786_3262273799982437331_n.jpg?stp=dst-jpg_e35_tt6&_nc_ht=instagram.fbhk1-4.fna.fbcdn.net&_nc_cat=102&_nc_oc=Q6cZ2QHHpibXBwkkYREhypZpew140bZPQbx9vFpJmgGXlquy5XXQR0SASXlUhAxAvHtaiT0&_nc_ohc=AHS0Iwl4FooQ7kNvwHkh_Jf&_nc_gid=e5mGv2vdFcvv89Ua151bSA&edm=AOQ1c0wBAAAA&ccb=7-5&oh=00_AfOPeNIA_-FX2RFFPiY4665LV-c46WcgH96eSvuymUeE4g&oe=684F0075&_nc_sid=8b3546",
            "likesCount": 94,
            "videoDuration": 90.666,
            "videoViewCount": 349,
            "id": "2413122881641150062",
            "hashtags": [
                "followforfollowbacks",
                "followersreal",
                "fff\ud83d\udc8b",
                "fff",
                "nagpur",
                "nagpurblogger",
                "nagpurfashion",
                "acneskin",
                "acneproneskincare",
                "acnescars",
                "mumbaiblogger",
                "jaipurblogger",
                "lakme",
                "trysugar",
                "pr",
                "collaboration",
                "collab",
                "neem",
                "facepack",
                "facepackselfie",
                "facepacks",
                "mondaymood"
            ],
            "mentions": [],
            "url": "https://www.instagram.com/p/CF9Inm_lnZu/",
            "firstComment": "",
            "latestComments": [],
            "images": [],
            "videoUrl": "https://instagram.fbhk1-3.fna.fbcdn.net/o1/v/t16/f2/m84/AQMbhNPUiiDkClIdYLFnggN0om4p6yctpWlDldsH618US4n5YkiI-O64Z7zuptfhJ4Xhocz1zHqxzSZ9L26DDFxDFbnmzp2cBYs1RS0.mp4?stp=dst-mp4&efg=eyJxZV9ncm91cHMiOiJbXCJpZ193ZWJfZGVsaXZlcnlfdnRzX290ZlwiXSIsInZlbmNvZGVfdGFnIjoidnRzX3ZvZF91cmxnZW4uaWd0di5jMi43MjAuYmFzZWxpbmUifQ&_nc_cat=101&vs=3569047773309483_852350863&_nc_vs=HBksFQIYTGlnX2JhY2tmaWxsX3RpbWVsaW5lX3ZvZC8zQzQzNDE4MUUyQzg1OTk2NDMxODcwRjdFRUFBMjhBQl92aWRlb19kYXNoaW5pdC5tcDQVAALIARIAFQIYOnBhc3N0aHJvdWdoX2V2ZXJzdG9yZS9HRjBlTXhlNUVINUFWVnNDQUk4cndEYUw4Uk43YnBrd0FBQUYVAgLIARIAKAAYABsBiAd1c2Vfb2lsATEVAAAmuOnB8tTnwz8VAigCQzMsF0BWqp%2B%2Bdsi0GBJkYXNoX2Jhc2VsaW5lXzFfdjERAHXsB2XCngEA&ccb=9-4&oh=00_AfNMnsQxJdMlHNqtt99dfX4fC6TwLuMZbUhYEpsgNYqP-g&oe=684AE2BB&_nc_sid=8b3546",
            "alt": null,
            "timestamp": "2020-10-05T08:31:53.000Z",
            "childPosts": [],
            "ownerUsername": "_urvashi_lalwani_",
            "ownerId": "32419739756",
            "productType": "igtv",
            "isCommentsDisabled": false
        }
    ],
    "postsCount": 1243,
    "latestPosts": [
        {
            "id": "3615600830553281925",
            "type": "Video",
            "shortCode": "DItMcySvFWF",
            "caption": "Outfits that I wore at my BHAIYA KI SHAADI\u2728\u2665\ufe0f\n.\n.\n#weddingout #weddingoutfits #outfits #outfitoftoday #shadi #shadivibes\u2b50\ufe0f",
            "hashtags": [
                "weddingout",
                "weddingoutfits",
                "outfits",
                "outfitoftoday",
                "shadi",
                "shadivibes\u2b50\ufe0f"
            ],
            "mentions": [],
            "url": "https://www.instagram.com/p/DItMcySvFWF/",
            "commentsCount": 4,
            "dimensionsHeight": 1920,
            "dimensionsWidth": 1080,
            "displayUrl": "https://instagram.fbhk1-2.fna.fbcdn.net/v/t51.2885-15/491498976_18062302019083757_1130254968447525749_n.jpg?stp=dst-jpg_e35_p1080x1080_sh0.08_tt6&_nc_ht=instagram.fbhk1-2.fna.fbcdn.net&_nc_cat=105&_nc_oc=Q6cZ2QHHpibXBwkkYREhypZpew140bZPQbx9vFpJmgGXlquy5XXQR0SASXlUhAxAvHtaiT0&_nc_ohc=Z8h2k0TqK2MQ7kNvwFPaDAo&_nc_gid=e5mGv2vdFcvv89Ua151bSA&edm=AOQ1c0wBAAAA&ccb=7-5&oh=00_AfO-lw2XKOaGGIFNmMRO-uSYUGrKPx6xHlpudtApH0d1rg&oe=684EE966&_nc_sid=8b3546",
            "images": [],
            "videoUrl": "https://instagram.fbhk1-3.fna.fbcdn.net/o1/v/t16/f2/m86/AQOHUuw_-hE-L4-FKnUlrCiGyBdF-Z-AyC0P-_zOpMSYMt__EFDd59nql8ELfeBVkjgQNIci_tMbpvnIvmllls1PMlE-5d9WCFvklDs.mp4?stp=dst-mp4&efg=eyJxZV9ncm91cHMiOiJbXCJpZ193ZWJfZGVsaXZlcnlfdnRzX290ZlwiXSIsInZlbmNvZGVfdGFnIjoidnRzX3ZvZF91cmxnZW4uY2xpcHMuYzIuNzIwLmJhc2VsaW5lIn0&_nc_cat=104&vs=9629591877076438_936060736&_nc_vs=HBksFQIYUmlnX3hwdl9yZWVsc19wZXJtYW5lbnRfc3JfcHJvZC85MzRCNzRFNEJDRkZGNkU0RDFCRDRGMDVGQzQ4REVBNl92aWRlb19kYXNoaW5pdC5tcDQVAALIARIAFQIYOnBhc3N0aHJvdWdoX2V2ZXJzdG9yZS9HTmtMU2gzSGVReVNPVTRFQU9GX2FYN2doZEowYnFfRUFBQUYVAgLIARIAKAAYABsAFQAAJuS8sa6Dq80%2FFQIoAkMzLBdAOHdLxqfvnhgSZGFzaF9iYXNlbGluZV8xX3YxEQB1%2Fgdl5p0BAA%3D%3D&ccb=9-4&oh=00_AfOurVGnyqsYw2XdxOCian6n-jDeABes3lYIqihUBrSghg&oe=684B00D8&_nc_sid=8b3546",
            "alt": null,
            "likesCount": 95,
            "videoViewCount": 1487,
            "timestamp": "2025-04-21T11:00:44.000Z",
            "childPosts": [],
            "ownerUsername": "_urvashi_lalwani_",
            "ownerId": "32419739756",
            "productType": "clips",
            "isPinned": true,
            "musicInfo": {
                "artist_name": "Shreya Ghoshal",
                "song_name": "O Bekhabar",
                "uses_original_audio": false,
                "should_mute_audio": false,
                "should_mute_audio_reason": "",
                "audio_id": "284222918879307"
            },
            "isCommentsDisabled": false
        },
        {
            "id": "3651938611302767194",
            "type": "Video",
            "shortCode": "DKuStF0PBpa",
            "caption": "A miracle that saved my skin.\n.\n.\n.\n#riceextract #faceshop #skincare #ad",
            "hashtags": [
                "riceextract",
                "faceshop",
                "skincare",
                "ad"
            ],
            "mentions": [],
            "url": "https://www.instagram.com/p/DKuStF0PBpa/",
            "commentsCount": 0,
            "dimensionsHeight": 1333,
            "dimensionsWidth": 750,
            "displayUrl": "https://instagram.fbhk1-2.fna.fbcdn.net/v/t51.2885-15/505425710_18066982202083757_8821270642036484665_n.jpg?stp=dst-jpg_e15_tt6&_nc_ht=instagram.fbhk1-2.fna.fbcdn.net&_nc_cat=105&_nc_oc=Q6cZ2QHHpibXBwkkYREhypZpew140bZPQbx9vFpJmgGXlquy5XXQR0SASXlUhAxAvHtaiT0&_nc_ohc=chOdrxVRxG0Q7kNvwFaWVxM&_nc_gid=e5mGv2vdFcvv89Ua151bSA&edm=AOQ1c0wBAAAA&ccb=7-5&oh=00_AfMFYSqjOpFOT6bKL9jYHt1Lz9mIgGa8-rR8Fh8FqRqGjA&oe=684EE45E&_nc_sid=8b3546",
            "images": [],
            "videoUrl": "https://instagram.fbhk1-3.fna.fbcdn.net/o1/v/t16/f2/m86/AQNmTIOfEQXA5zlqhYfdckP8XvsSY6S8szA5NHiOjaJ-zzw50wU59WxI0MZAEdA1lKNsqphjDE_MlgFlglEXT800LTKWk3O0934eaBs.mp4?stp=dst-mp4&efg=eyJxZV9ncm91cHMiOiJbXCJpZ193ZWJfZGVsaXZlcnlfdnRzX290ZlwiXSIsInZlbmNvZGVfdGFnIjoidnRzX3ZvZF91cmxnZW4uY2xpcHMuYzIuNzIwLmJhc2VsaW5lIn0&_nc_cat=100&vs=1122515816353316_3279950518&_nc_vs=HBksFQIYUmlnX3hwdl9yZWVsc19wZXJtYW5lbnRfc3JfcHJvZC83QjRGQzExRTg5QjM2NEFBRjFCMEZDQzhBNUM0MDI4MF92aWRlb19kYXNoaW5pdC5tcDQVAALIARIAFQIYOnBhc3N0aHJvdWdoX2V2ZXJzdG9yZS9HRFZrTEI0bTN0blRwXzREQUhyUlFGTUZZU1plYnFfRUFBQUYVAgLIARIAKAAYABsAFQAAJuTzwJrSldA%2FFQIoAkMzLBdAQ7ul41P3zxgSZGFzaF9iYXNlbGluZV8xX3YxEQB1%2Fgdl5p0BAA%3D%3D&ccb=9-4&oh=00_AfN8VQwMWYw4Ro_9GHxiepji7Z3nLfJlbKTVwl7AabBaOQ&oe=684B05C0&_nc_sid=8b3546",
            "alt": null,
            "likesCount": 20,
            "videoViewCount": 0,
            "timestamp": "2025-06-10T14:19:22.000Z",
            "childPosts": [],
            "ownerUsername": "_urvashi_lalwani_",
            "ownerId": "32419739756",
            "productType": "clips",
            "taggedUsers": [
                {
                    "full_name": "The Face Shop India",
                    "id": "3567473246",
                    "is_verified": false,
                    "profile_pic_url": "https://instagram.fbhk1-4.fna.fbcdn.net/v/t51.2885-19/451211873_1489326691943492_4683443294855911273_n.jpg?stp=dst-jpg_e0_s150x150_tt6&_nc_ht=instagram.fbhk1-4.fna.fbcdn.net&_nc_cat=1&_nc_oc=Q6cZ2QHHpibXBwkkYREhypZpew140bZPQbx9vFpJmgGXlquy5XXQR0SASXlUhAxAvHtaiT0&_nc_ohc=hfTSzpqpFcIQ7kNvwE6WWHe&_nc_gid=e5mGv2vdFcvv89Ua151bSA&edm=AOQ1c0wBAAAA&ccb=7-5&oh=00_AfOXZDUegxg_E-W2enTvmO4RzX4GQbbMHYDktaXpRkSpJQ&oe=684EE814&_nc_sid=8b3546",
                    "username": "thefaceshopindia_official"
                }
            ],
            "isCommentsDisabled": false
        },
        {
            "id": "3650287762063294096",
            "type": "Video",
            "shortCode": "DKobWEpvP6Q",
            "caption": "Pampered and how\u263a\ufe0f\u2728\u2665\ufe0f \n@flipkart \n.\n(PR , flipkart , GlamFest2025 , creator. )",
            "hashtags": [],
            "mentions": [
                "flipkart"
            ],
            "url": "https://www.instagram.com/p/DKobWEpvP6Q/",
            "commentsCount": 0,
            "dimensionsHeight": 1333,
            "dimensionsWidth": 750,
            "displayUrl": "https://instagram.fbhk1-2.fna.fbcdn.net/v/t51.2885-15/504489899_18066771437083757_4517087981585513873_n.jpg?stp=dst-jpg_e15_tt6&_nc_ht=instagram.fbhk1-2.fna.fbcdn.net&_nc_cat=105&_nc_oc=Q6cZ2QHHpibXBwkkYREhypZpew140bZPQbx9vFpJmgGXlquy5XXQR0SASXlUhAxAvHtaiT0&_nc_ohc=D-Jtm1SeNL0Q7kNvwFuBVz4&_nc_gid=e5mGv2vdFcvv89Ua151bSA&edm=AOQ1c0wBAAAA&ccb=7-5&oh=00_AfOIVtwvXV2oImLf9ON5-SQ-D_sekgifq2u6O4PfKpXdIQ&oe=684F08B1&_nc_sid=8b3546",
            "images": [],
            "videoUrl": "https://instagram.fbhk1-3.fna.fbcdn.net/o1/v/t16/f2/m86/AQOOLISiOIeQ9tk-6kCe6a3CAbRQ941CROvovq3aFb8wvJqgBWiR8B_rAfUPaf45nPAYCQ-rFEO27fzH6H5jrn3aeSbmx4aQRIUxzkQ.mp4?stp=dst-mp4&efg=eyJxZV9ncm91cHMiOiJbXCJpZ193ZWJfZGVsaXZlcnlfdnRzX290ZlwiXSIsInZlbmNvZGVfdGFnIjoidnRzX3ZvZF91cmxnZW4uY2xpcHMuYzIuNzIwLmJhc2VsaW5lIn0&_nc_cat=103&vs=692356843647816_1379657595&_nc_vs=HBksFQIYUmlnX3hwdl9yZWVsc19wZXJtYW5lbnRfc3JfcHJvZC9BMjRBNjNGNkZDQjhDNkI0MkExNjk3MjkzQUU4NEM4M192aWRlb19kYXNoaW5pdC5tcDQVAALIARIAFQIYOnBhc3N0aHJvdWdoX2V2ZXJzdG9yZS9HTm1zNkIxM2xUWjNEc0VFQUR5bzlVMldjUmNBYnFfRUFBQUYVAgLIARIAKAAYABsAFQAAJuTyu%2F7bhNA%2FFQIoAkMzLBdAPbul41P3zxgSZGFzaF9iYXNlbGluZV8xX3YxEQB1%2Fgdl5p0BAA%3D%3D&ccb=9-4&oh=00_AfPYJ69YUh83Hqn2z4rb5WpcbdeZPK_Pp3-w2B4_5GNSVw&oe=684B13CA&_nc_sid=8b3546",
            "alt": null,
            "likesCount": 19,
            "videoViewCount": 0,
            "timestamp": "2025-06-08T07:39:30.000Z",
            "childPosts": [],
            "ownerUsername": "_urvashi_lalwani_",
            "ownerId": "32419739756",
            "productType": "clips",
            "isCommentsDisabled": false
        },
        {
            "id": "3649748091602550346",
            "type": "Video",
            "shortCode": "DKmgo1XoT5K",
            "caption": "They say good things take time\u2026 but great skin? Just takes the right secret. \ud83d\udc40\u2728\n\nI\u2019ve found something that:\n\u2714\ufe0f Gives a matte finish\n\u2714\ufe0f Minimises pores\n\u2714\ufe0f Protects from sun damage\n\u2714\ufe0f Prevents premature ageing\n\u2026and so much more.\n\nWant to know what it is?\nYou\u2019ll have to wait for my next reel. \ud83d\ude09\ud83e\udee3 Stay tuned! #SkinSecret #ComingSoon #SkincareThatWorks\n#ad",
            "hashtags": [
                "SkinSecret",
                "ComingSoon",
                "SkincareThatWorks",
                "ad"
            ],
            "mentions": [],
            "url": "https://www.instagram.com/p/DKmgo1XoT5K/",
            "commentsCount": 0,
            "dimensionsHeight": 1918,
            "dimensionsWidth": 1080,
            "displayUrl": "https://instagram.fbhk1-2.fna.fbcdn.net/v/t51.2885-15/504485137_18066690296083757_8781233359993802767_n.jpg?stp=dst-jpg_e35_p1080x1080_sh0.08_tt6&_nc_ht=instagram.fbhk1-2.fna.fbcdn.net&_nc_cat=105&_nc_oc=Q6cZ2QHHpibXBwkkYREhypZpew140bZPQbx9vFpJmgGXlquy5XXQR0SASXlUhAxAvHtaiT0&_nc_ohc=Xu57lLXSf4kQ7kNvwFkIiTD&_nc_gid=e5mGv2vdFcvv89Ua151bSA&edm=AOQ1c0wBAAAA&ccb=7-5&oh=00_AfPHbsFwUZGIQJx3I0RlF7-Eioy8aHnbjJDg2WuMD637bQ&oe=684F0A4D&_nc_sid=8b3546",
            "images": [],
            "videoUrl": "https://instagram.fbhk1-3.fna.fbcdn.net/o1/v/t16/f2/m86/AQOiduYNOFl7WwA9tMoSkDjzZEuE-EIIDB6Zq6NegEIw1GWR-y8mH9hsyS_IxlvtG7as7nkrxqlddIy4Tv1UJE1d-c289KRfS7dFRAA.mp4?stp=dst-mp4&efg=eyJxZV9ncm91cHMiOiJbXCJpZ193ZWJfZGVsaXZlcnlfdnRzX290ZlwiXSIsInZlbmNvZGVfdGFnIjoidnRzX3ZvZF91cmxnZW4uY2xpcHMuYzIuNzIwLmJhc2VsaW5lIn0&_nc_cat=100&vs=596007563028889_543088677&_nc_vs=HBksFQIYUmlnX3hwdl9yZWVsc19wZXJtYW5lbnRfc3JfcHJvZC8zRjRCOUE2QzUwMzc1RTY1QkI3N0QxRTJCNTJGREY4NF92aWRlb19kYXNoaW5pdC5tcDQVAALIARIAFQIYOnBhc3N0aHJvdWdoX2V2ZXJzdG9yZS9HR1g5SkI2MDlPRVk5b3dDQUlNaGo0Vkw3eEkwYmtZTEFBQUYVAgLIARIAKAAYABsAFQAAJuTXq7Du%2Fs8%2FFQIoAkMzLBdASHdsi0OVgRgSZGFzaF9iYXNlbGluZV8xX3YxEQB1%2Fgdl5p0BAA%3D%3D&ccb=9-4&oh=00_AfPI7vsH8AkdIxN5NbI6ThtaBhVzgv6wjDUrnJW4RpYy_g&oe=684AFC1B&_nc_sid=8b3546",
            "alt": null,
            "likesCount": 18,
            "videoViewCount": 0,
            "timestamp": "2025-06-07T13:47:17.000Z",
            "childPosts": [],
            "ownerUsername": "_urvashi_lalwani_",
            "ownerId": "32419739756",
            "productType": "clips",
            "taggedUsers": [
                {
                    "full_name": "Personal Touch Skincare \u00ae",
                    "id": "52729066671",
                    "is_verified": false,
                    "profile_pic_url": "https://instagram.fbhk1-4.fna.fbcdn.net/v/t51.2885-19/472453811_611086074809570_405416685382335378_n.jpg?stp=dst-jpg_e0_s150x150_tt6&_nc_ht=instagram.fbhk1-4.fna.fbcdn.net&_nc_cat=1&_nc_oc=Q6cZ2QHHpibXBwkkYREhypZpew140bZPQbx9vFpJmgGXlquy5XXQR0SASXlUhAxAvHtaiT0&_nc_ohc=q_HJ8oMNbdgQ7kNvwG1_T8i&_nc_gid=e5mGv2vdFcvv89Ua151bSA&edm=AOQ1c0wBAAAA&ccb=7-5&oh=00_AfMrjvZTv4fXM8fPFloBMSY2lPPTAlaNHx4Y91AV7fL_TA&oe=684EE011&_nc_sid=8b3546",
                    "username": "personaltouchskincare"
                }
            ],
            "isCommentsDisabled": false
        },
        {
            "id": "3649660614636227496",
            "type": "Video",
            "shortCode": "DKmMv4GIEuo",
            "caption": "Glow smarter with Kiro \ud83d\udc84 \u2014 clean, cruelty-free beauty now at up to 40% off during the #FlipkartGlamUpSale! \u2728\n#TrendItFlipkartIt #FlipkartBeautySale #KiroBeauty\n@flipkart @flipkartlifestyle @kirobeauty #glamup2025 #glamup2025 #glamup2025\n#glamup2025",
            "hashtags": [
                "FlipkartGlamUpSale!",
                "TrendItFlipkartIt",
                "FlipkartBeautySale",
                "KiroBeauty",
                "glamup2025"
            ],
            "mentions": [
                "flipkart",
                "flipkartlifestyle",
                "kirobeauty"
            ],
            "url": "https://www.instagram.com/p/DKmMv4GIEuo/",
            "commentsCount": 0,
            "dimensionsHeight": 1333,
            "dimensionsWidth": 750,
            "displayUrl": "https://instagram.fbhk1-2.fna.fbcdn.net/v/t51.2885-15/503500844_18066678227083757_2830057127603256808_n.jpg?stp=dst-jpg_e15_tt6&_nc_ht=instagram.fbhk1-2.fna.fbcdn.net&_nc_cat=105&_nc_oc=Q6cZ2QHHpibXBwkkYREhypZpew140bZPQbx9vFpJmgGXlquy5XXQR0SASXlUhAxAvHtaiT0&_nc_ohc=WC9O_aDMFrIQ7kNvwGr54w1&_nc_gid=e5mGv2vdFcvv89Ua151bSA&edm=AOQ1c0wBAAAA&ccb=7-5&oh=00_AfO6xM7BxHNJZL6IwzZdFMIB4FMfCnPoplVdL-vQf0ri3w&oe=684EF236&_nc_sid=8b3546",
            "images": [],
            "videoUrl": "https://instagram.fbhk1-2.fna.fbcdn.net/o1/v/t16/f2/m86/AQPNBqXIZHLI_RpZInmGxKzHV4_Yd7ev0sJR6FinfhJPAEanqUFSRAc8M280g0e0lthoM364oTZKJ6n8KVY-3QrImfLuCfm6s6db7-8.mp4?stp=dst-mp4&efg=eyJxZV9ncm91cHMiOiJbXCJpZ193ZWJfZGVsaXZlcnlfdnRzX290ZlwiXSIsInZlbmNvZGVfdGFnIjoidnRzX3ZvZF91cmxnZW4uY2xpcHMuYzIuNzIwLmJhc2VsaW5lIn0&_nc_cat=109&vs=1627994597861720_3226857550&_nc_vs=HBksFQIYUmlnX3hwdl9yZWVsc19wZXJtYW5lbnRfc3JfcHJvZC9FNTQwNTY4MjU5QTlENjM2REU5NUZENjZFNDYzQUZBQl92aWRlb19kYXNoaW5pdC5tcDQVAALIARIAFQIYOnBhc3N0aHJvdWdoX2V2ZXJzdG9yZS9HQUx4RUI1NEtBV0xrQnNnQURtZU5QNHU2RzExYnFfRUFBQUYVAgLIARIAKAAYABsAFQAAJuSOwbDo%2Fc8%2FFQIoAkMzLBdAJe6XjU%2FfOxgSZGFzaF9iYXNlbGluZV8xX3YxEQB1%2Fgdl5p0BAA%3D%3D&ccb=9-4&oh=00_AfNtWZKIUT4nqTolFko_Fs-FmtC8qT59i83Tikwe2a-rcg&oe=684B0462&_nc_sid=8b3546",
            "alt": null,
            "likesCount": 13,
            "videoViewCount": 0,
            "timestamp": "2025-06-07T10:55:00.000Z",
            "childPosts": [],
            "ownerUsername": "_urvashi_lalwani_",
            "ownerId": "32419739756",
            "productType": "clips",
            "musicInfo": {
                "artist_name": "WizTheMc, bees & honey, Tyla",
                "song_name": "Show Me Love (with Tyla)",
                "uses_original_audio": false,
                "should_mute_audio": false,
                "should_mute_audio_reason": "",
                "audio_id": "1424404392251203"
            },
            "isCommentsDisabled": false
        },
        {
            "id": "3649656426464343452",
            "type": "Sidecar",
            "shortCode": "DKmLy7joPWc",
            "caption": "Level up your glam with Lakme! \ud83d\udc84 Unmissable deals on your beauty must-haves at the #FlipkartGlamUpSale.\n#TrendItFlipkartIt #FlipkartBeautySale #Lakme\n@flipkart @flipkartlifestyle @lakmeindia #glamup2025 #glamup2025 #glamup2025\n#glamup2025",
            "hashtags": [
                "FlipkartGlamUpSale.",
                "TrendItFlipkartIt",
                "FlipkartBeautySale",
                "Lakme",
                "glamup2025"
            ],
            "mentions": [
                "flipkart",
                "flipkartlifestyle",
                "lakmeindia"
            ],
            "url": "https://www.instagram.com/p/DKmLy7joPWc/",
            "commentsCount": 0,
            "dimensionsHeight": 1437,
            "dimensionsWidth": 1080,
            "displayUrl": "https://instagram.fbhk1-2.fna.fbcdn.net/v/t51.2885-15/503613436_18066676937083757_2800653575428472583_n.jpg?stp=dst-jpg_e35_p1080x1080_sh0.08_tt6&_nc_ht=instagram.fbhk1-2.fna.fbcdn.net&_nc_cat=105&_nc_oc=Q6cZ2QHHpibXBwkkYREhypZpew140bZPQbx9vFpJmgGXlquy5XXQR0SASXlUhAxAvHtaiT0&_nc_ohc=RqB2xZQrblEQ7kNvwFLGJuF&_nc_gid=e5mGv2vdFcvv89Ua151bSA&edm=AOQ1c0wBAAAA&ccb=7-5&ig_cache_key=MzY0OTY1NjQxMTU0OTM1MzA0Nw%3D%3D.3-ccb7-5&oh=00_AfOSJu2I_DGJ63WrOQ_D-dTxatzqaVvGZ_PAoRyd3JcL3A&oe=684F015B&_nc_sid=8b3546",
            "images": [
                "https://instagram.fbhk1-2.fna.fbcdn.net/v/t51.2885-15/503613436_18066676937083757_2800653575428472583_n.jpg?stp=dst-jpg_e35_p1080x1080_sh0.08_tt6&_nc_ht=instagram.fbhk1-2.fna.fbcdn.net&_nc_cat=105&_nc_oc=Q6cZ2QHHpibXBwkkYREhypZpew140bZPQbx9vFpJmgGXlquy5XXQR0SASXlUhAxAvHtaiT0&_nc_ohc=RqB2xZQrblEQ7kNvwFLGJuF&_nc_gid=e5mGv2vdFcvv89Ua151bSA&edm=AOQ1c0wBAAAA&ccb=7-5&ig_cache_key=MzY0OTY1NjQxMTU0OTM1MzA0Nw%3D%3D.3-ccb7-5&oh=00_AfOSJu2I_DGJ63WrOQ_D-dTxatzqaVvGZ_PAoRyd3JcL3A&oe=684F015B&_nc_sid=8b3546",
                "https://instagram.fbhk1-2.fna.fbcdn.net/v/t51.2885-15/503570814_18066677195083757_5790839126770697109_n.jpg?stp=dst-jpg_e15_tt6&_nc_ht=instagram.fbhk1-2.fna.fbcdn.net&_nc_cat=105&_nc_oc=Q6cZ2QHHpibXBwkkYREhypZpew140bZPQbx9vFpJmgGXlquy5XXQR0SASXlUhAxAvHtaiT0&_nc_ohc=Rd-2amoAIlkQ7kNvwEEYi8e&_nc_gid=e5mGv2vdFcvv89Ua151bSA&edm=AOQ1c0wBAAAA&ccb=7-5&oh=00_AfPvwSbz-49GfQKKTnTbHgxq72WiR-Lx36wuk1rkGyj9-Q&oe=684EF7C7&_nc_sid=8b3546",
                "https://instagram.fbhk1-2.fna.fbcdn.net/v/t51.2885-15/504347689_18066677153083757_1252833840200163304_n.jpg?stp=dst-jpg_e35_p1080x1080_sh0.08_tt6&_nc_ht=instagram.fbhk1-2.fna.fbcdn.net&_nc_cat=105&_nc_oc=Q6cZ2QHHpibXBwkkYREhypZpew140bZPQbx9vFpJmgGXlquy5XXQR0SASXlUhAxAvHtaiT0&_nc_ohc=6Fg9PQws69QQ7kNvwHOMlDM&_nc_gid=e5mGv2vdFcvv89Ua151bSA&edm=AOQ1c0wBAAAA&ccb=7-5&ig_cache_key=MzY0OTY1NjQxMTU0OTQ4NDM2Ng%3D%3D.3-ccb7-5&oh=00_AfPvX_GSTh0KCmGccYCnU_VnMnnooMF_D8EbfQhy_ZdBLQ&oe=684ED763&_nc_sid=8b3546"
            ],
            "alt": "Photo by \ud835\ude50\ud835\ude67\ud835\ude6b\ud835\ude56\ud835\ude68\ud835\ude5d\ud835\ude5e \ud835\ude47\ud835\ude56\ud835\ude61\ud835\ude6c\ud835\ude56\ud835\ude63\ud835\ude5e on June 07, 2025. May be an image of 1 person, magazine, poster and text that says 'Take HYA with 1AK 1AKME ME 9y 9'.",
            "likesCount": 40,
            "timestamp": "2025-06-07T10:42:51.000Z",
            "childPosts": [
                {
                    "id": "3649656411549353047",
                    "type": "Image",
                    "shortCode": "DKmLytqoERX",
                    "caption": "",
                    "hashtags": [],
                    "mentions": [],
                    "url": "https://www.instagram.com/p/DKmLytqoERX/",
                    "commentsCount": 0,
                    "firstComment": "",
                    "latestComments": [],
                    "dimensionsHeight": 1437,
                    "dimensionsWidth": 1080,
                    "displayUrl": "https://instagram.fbhk1-2.fna.fbcdn.net/v/t51.2885-15/503613436_18066676937083757_2800653575428472583_n.jpg?stp=dst-jpg_e35_p1080x1080_sh0.08_tt6&_nc_ht=instagram.fbhk1-2.fna.fbcdn.net&_nc_cat=105&_nc_oc=Q6cZ2QHHpibXBwkkYREhypZpew140bZPQbx9vFpJmgGXlquy5XXQR0SASXlUhAxAvHtaiT0&_nc_ohc=RqB2xZQrblEQ7kNvwFLGJuF&_nc_gid=e5mGv2vdFcvv89Ua151bSA&edm=AOQ1c0wBAAAA&ccb=7-5&ig_cache_key=MzY0OTY1NjQxMTU0OTM1MzA0Nw%3D%3D.3-ccb7-5&oh=00_AfOSJu2I_DGJ63WrOQ_D-dTxatzqaVvGZ_PAoRyd3JcL3A&oe=684F015B&_nc_sid=8b3546",
                    "images": [],
                    "alt": "Photo by \ud835\ude50\ud835\ude67\ud835\ude6b\ud835\ude56\ud835\ude68\ud835\ude5d\ud835\ude5e \ud835\ude47\ud835\ude56\ud835\ude61\ud835\ude6c\ud835\ude56\ud835\ude63\ud835\ude5e on June 07, 2025. May be an image of 1 person, magazine, poster and text that says 'Take HYA with 1AK 1AKME ME 9y 9'.",
                    "likesCount": null,
                    "timestamp": null,
                    "childPosts": [],
                    "ownerUsername": "_urvashi_lalwani_",
                    "ownerId": "32419739756"
                },
                {
                    "id": "3649654778094586237",
                    "type": "Video",
                    "shortCode": "DKmLa8ZIol9",
                    "caption": "",
                    "hashtags": [],
                    "mentions": [],
                    "url": "https://www.instagram.com/p/DKmLa8ZIol9/",
                    "commentsCount": 0,
                    "firstComment": "",
                    "latestComments": [],
                    "dimensionsHeight": 1000,
                    "dimensionsWidth": 750,
                    "displayUrl": "https://instagram.fbhk1-2.fna.fbcdn.net/v/t51.2885-15/503570814_18066677195083757_5790839126770697109_n.jpg?stp=dst-jpg_e15_tt6&_nc_ht=instagram.fbhk1-2.fna.fbcdn.net&_nc_cat=105&_nc_oc=Q6cZ2QHHpibXBwkkYREhypZpew140bZPQbx9vFpJmgGXlquy5XXQR0SASXlUhAxAvHtaiT0&_nc_ohc=Rd-2amoAIlkQ7kNvwEEYi8e&_nc_gid=e5mGv2vdFcvv89Ua151bSA&edm=AOQ1c0wBAAAA&ccb=7-5&oh=00_AfPvwSbz-49GfQKKTnTbHgxq72WiR-Lx36wuk1rkGyj9-Q&oe=684EF7C7&_nc_sid=8b3546",
                    "images": [],
                    "videoUrl": "https://instagram.fbhk1-2.fna.fbcdn.net/o1/v/t16/f2/m367/AQMFVYH3GigN7MDJ_gVYMahYST4HdMIDxB7vfZBPv-Ou3Gw79ALA4i6Vl6vxnOBHr9WOcHqGr31yXsLiB3t-bNp6exy1lD-UhWI17Gc.mp4?stp=dst-mp4&efg=eyJxZV9ncm91cHMiOiJbXCJpZ193ZWJfZGVsaXZlcnlfdnRzX290ZlwiXSIsInZlbmNvZGVfdGFnIjoidnRzX3ZvZF91cmxnZW4uY2Fyb3VzZWxfaXRlbS5jMi4xMDgwLmJhc2VsaW5lIn0&_nc_cat=110&vs=1459699625017605_2743477759&_nc_vs=HBksFQIYQGlnX2VwaGVtZXJhbC8xMTQwQ0JGQ0RERDY0MEQ3QTEzMjIzMkVENzQxMEY5OV92aWRlb19kYXNoaW5pdC5tcDQVAALIARIAFQIYOnBhc3N0aHJvdWdoX2V2ZXJzdG9yZS9HTTRJN2gzZG4zTW1RQUlDQUFjSmt3R0hKdWQ3YmtZTEFBQUYVAgLIARIAKAAYABsAFQAAJuTwkq7h%2Fc8%2FFQIoAkMzLBdAI4gxJul41RgWZGFzaF9iYXNlbGluZV8xMDgwcF92MREAde4HZcSeAQA%3D&ccb=9-4&oh=00_AfPuCge80WTkYcRl7r2byWqSwINz20OQTlhbjSUY9byxkQ&oe=684B09AF&_nc_sid=8b3546",
                    "alt": null,
                    "likesCount": null,
                    "videoViewCount": 0,
                    "timestamp": null,
                    "childPosts": [],
                    "ownerUsername": "_urvashi_lalwani_",
                    "ownerId": "32419739756"
                },
                {
                    "id": "3649656411549484366",
                    "type": "Image",
                    "shortCode": "DKmLytqokVO",
                    "caption": "",
                    "hashtags": [],
                    "mentions": [],
                    "url": "https://www.instagram.com/p/DKmLytqokVO/",
                    "commentsCount": 0,
                    "firstComment": "",
                    "latestComments": [],
                    "dimensionsHeight": 1440,
                    "dimensionsWidth": 1080,
                    "displayUrl": "https://instagram.fbhk1-2.fna.fbcdn.net/v/t51.2885-15/504347689_18066677153083757_1252833840200163304_n.jpg?stp=dst-jpg_e35_p1080x1080_sh0.08_tt6&_nc_ht=instagram.fbhk1-2.fna.fbcdn.net&_nc_cat=105&_nc_oc=Q6cZ2QHHpibXBwkkYREhypZpew140bZPQbx9vFpJmgGXlquy5XXQR0SASXlUhAxAvHtaiT0&_nc_ohc=6Fg9PQws69QQ7kNvwHOMlDM&_nc_gid=e5mGv2vdFcvv89Ua151bSA&edm=AOQ1c0wBAAAA&ccb=7-5&ig_cache_key=MzY0OTY1NjQxMTU0OTQ4NDM2Ng%3D%3D.3-ccb7-5&oh=00_AfPvX_GSTh0KCmGccYCnU_VnMnnooMF_D8EbfQhy_ZdBLQ&oe=684ED763&_nc_sid=8b3546",
                    "images": [],
                    "alt": "Photo by \ud835\ude50\ud835\ude67\ud835\ude6b\ud835\ude56\ud835\ude68\ud835\ude5d\ud835\ude5e \ud835\ude47\ud835\ude56\ud835\ude61\ud835\ude6c\ud835\ude56\ud835\ude63\ud835\ude5e on June 07, 2025. May be an image of one or more people, fingernails, makeup, fragrance, cosmetics, perfume and text.",
                    "likesCount": null,
                    "timestamp": null,
                    "childPosts": [],
                    "ownerUsername": "_urvashi_lalwani_",
                    "ownerId": "32419739756"
                }
            ],
            "ownerUsername": "_urvashi_lalwani_",
            "ownerId": "32419739756",
            "isCommentsDisabled": false
        },
        {
            "id": "3648255400650065163",
            "type": "Video",
            "shortCode": "DKhNPUlpcUL",
            "caption": "DIYs are fun\u2026 but for dark spots, I trust science \ud83c\udf3f\u2728\nShrumei\u2019s Dark Spot Corrector is powered by mushrooms & Oxyresveratrol \n\nLightweight, hydrating & super effective!\nNature meets science. Skin meets Shrumei \ud83c\udf3c\nA non irritating formula, Gentle enough for daily use.\nShop now on Nykaa, Amazon, Flipkart & shrumei.com\n\n#ShrumeiSkin #NaturalSkincare #DarkspotCorrector #SkincareRoutine #DarkSpots #pigmentation #ad",
            "hashtags": [
                "ShrumeiSkin",
                "NaturalSkincare",
                "DarkspotCorrector",
                "SkincareRoutine",
                "DarkSpots",
                "pigmentation",
                "ad"
            ],
            "mentions": [],
            "url": "https://www.instagram.com/p/DKhNPUlpcUL/",
            "commentsCount": 1,
            "dimensionsHeight": 1136,
            "dimensionsWidth": 640,
            "displayUrl": "https://instagram.fbhk1-1.fna.fbcdn.net/v/t51.2885-15/503805503_1268133021348023_8815133228992549625_n.jpg?stp=dst-jpg_e15_tt6&_nc_ht=instagram.fbhk1-1.fna.fbcdn.net&_nc_cat=111&_nc_oc=Q6cZ2QHHpibXBwkkYREhypZpew140bZPQbx9vFpJmgGXlquy5XXQR0SASXlUhAxAvHtaiT0&_nc_ohc=V3W-aD02wjQQ7kNvwEEfFIL&_nc_gid=e5mGv2vdFcvv89Ua151bSA&edm=AOQ1c0wBAAAA&ccb=7-5&oh=00_AfPNITOp4ZQbS40_sgLXYHAquQbF259AekSmKGTY1gh-cw&oe=684EF113&_nc_sid=8b3546",
            "images": [],
            "videoUrl": "https://instagram.fbhk1-4.fna.fbcdn.net/o1/v/t16/f2/m86/AQPVetHW2BgM9x-vCwMNr_rZ8RmU_C5IC0nwykNOGnvo99TgVG-rhAF0B0VGLhF-MlJLqV95V15OvVHPRoPuVzKn1zfTCFjUWd5vDBM.mp4?stp=dst-mp4&efg=eyJxZV9ncm91cHMiOiJbXCJpZ193ZWJfZGVsaXZlcnlfdnRzX290ZlwiXSIsInZlbmNvZGVfdGFnIjoidnRzX3ZvZF91cmxnZW4uY2xpcHMuYzIuNzIwLmJhc2VsaW5lIn0&_nc_cat=108&vs=1176102517538141_396007507&_nc_vs=HBksFQIYUmlnX3hwdl9yZWVsc19wZXJtYW5lbnRfc3JfcHJvZC8xMTQxNUU2NzIxRDdCNkQyMjNGOUNDNTAyQTY3RERBQ192aWRlb19kYXNoaW5pdC5tcDQVAALIARIAFQIYOnBhc3N0aHJvdWdoX2V2ZXJzdG9yZS9HSGg5OUIxUXdfWm1hNXNEQU51MDBMdWozY2QzYnFfRUFBQUYVAgLIARIAKAAYABsAFQAAJuSS49%2Fh7s8%2FFQIoAkMzLBdATSZmZmZmZhgSZGFzaF9iYXNlbGluZV8xX3YxEQB1%2Fgdl5p0BAA%3D%3D&ccb=9-4&oh=00_AfNIs62M8tuhGzNMc9LpqeXnq6MGwwZchrtdsK977fuJmA&oe=684B062A&_nc_sid=8b3546",
            "alt": null,
            "likesCount": 25,
            "videoViewCount": 0,
            "timestamp": "2025-06-05T12:20:35.000Z",
            "childPosts": [],
            "ownerUsername": "_urvashi_lalwani_",
            "ownerId": "32419739756",
            "productType": "clips",
            "taggedUsers": [
                {
                    "full_name": "SHRUMEI",
                    "id": "71712225340",
                    "is_verified": true,
                    "profile_pic_url": "https://instagram.fbhk1-2.fna.fbcdn.net/v/t51.2885-19/475563449_604403252295910_5185502906418402370_n.jpg?stp=dst-jpg_e0_s150x150_tt6&_nc_ht=instagram.fbhk1-2.fna.fbcdn.net&_nc_cat=110&_nc_oc=Q6cZ2QHHpibXBwkkYREhypZpew140bZPQbx9vFpJmgGXlquy5XXQR0SASXlUhAxAvHtaiT0&_nc_ohc=Fr2Rtd8kcZMQ7kNvwE2jvpi&_nc_gid=e5mGv2vdFcvv89Ua151bSA&edm=AOQ1c0wBAAAA&ccb=7-5&oh=00_AfMhAoi_a3ztwEIm2qgsDGP7cp9JeWjaKUeCC6l-Vl6lZg&oe=684EDB01&_nc_sid=8b3546",
                    "username": "shrumei.official"
                }
            ],
            "isCommentsDisabled": false
        },
        {
            "id": "3647588980070700839",
            "type": "Video",
            "shortCode": "DKe1toDvlcn",
            "caption": "Some face washes come and go\u2026 but @himalaya_facecare Neem Face Wash? This one stays.\n\ud83c\udf3f Now upgraded with 5 parts of Neem\n \ud83e\uddfc Clinically tested to:\n \u2714\ufe0f Remove pimples from Day 5\n \u2714\ufe0f Prevent them from coming back\n \ud83d\udce6 New look, same OG power\n \ud83d\udecd\ufe0f Available now on @flipkart\n#BestFacewashesForSensitiveSkin #HimalayaFaceCare\n #FlipkartGlamUpSale #FlipkartBeautySale #TrendItFlipkartIt\nTags:\n @himalaya_facecare @flipkart @flipkartlifestyle",
            "hashtags": [
                "BestFacewashesForSensitiveSkin",
                "HimalayaFaceCare",
                "FlipkartGlamUpSale",
                "FlipkartBeautySale",
                "TrendItFlipkartIt"
            ],
            "mentions": [
                "himalaya_facecare",
                "flipkart",
                "flipkartlifestyle"
            ],
            "url": "https://www.instagram.com/p/DKe1toDvlcn/",
            "commentsCount": 1,
            "dimensionsHeight": 1136,
            "dimensionsWidth": 640,
            "displayUrl": "https://instagram.fbhk1-2.fna.fbcdn.net/v/t51.2885-15/503129882_24395794946691561_8075798488465168293_n.jpg?stp=dst-jpg_e15_tt6&_nc_ht=instagram.fbhk1-2.fna.fbcdn.net&_nc_cat=109&_nc_oc=Q6cZ2QHHpibXBwkkYREhypZpew140bZPQbx9vFpJmgGXlquy5XXQR0SASXlUhAxAvHtaiT0&_nc_ohc=HO6aQFBqac4Q7kNvwHEC2b8&_nc_gid=e5mGv2vdFcvv89Ua151bSA&edm=AOQ1c0wBAAAA&ccb=7-5&oh=00_AfNMfTKl8dPo6bksR6HGLS3P2-cOKRfJBLf0_ao8-Ni0-A&oe=684EF185&_nc_sid=8b3546",
            "images": [],
            "videoUrl": "https://instagram.fbhk1-4.fna.fbcdn.net/o1/v/t16/f2/m86/AQNUS1Q3OSFrgnf8jTBHqTae5TvyrWm9MwNdL7PzpGpvOlL4_1fDM2sP3fYX_q6tFQSOR0JB8pj0xBnRauSGoWmzxd3TGSw_aRBARkw.mp4?stp=dst-mp4&efg=eyJxZV9ncm91cHMiOiJbXCJpZ193ZWJfZGVsaXZlcnlfdnRzX290ZlwiXSIsInZlbmNvZGVfdGFnIjoidnRzX3ZvZF91cmxnZW4uY2xpcHMuYzIuNzIwLmJhc2VsaW5lIn0&_nc_cat=102&vs=1248506173640945_3487702507&_nc_vs=HBksFQIYUmlnX3hwdl9yZWVsc19wZXJtYW5lbnRfc3JfcHJvZC9EQjQ1QzA4N0UyMTU5MUVBQjBBOTk0MDlERjBFRjNBNV92aWRlb19kYXNoaW5pdC5tcDQVAALIARIAFQIYOnBhc3N0aHJvdWdoX2V2ZXJzdG9yZS9HQ1U2Q1I3ZUlIVDg1Y29EQUs0T0IyVFVqaXBQYnFfRUFBQUYVAgLIARIAKAAYABsAFQAAJuTklpCt6M8%2FFQIoAkMzLBdARA2RaHKwIRgSZGFzaF9iYXNlbGluZV8xX3YxEQB1%2Fgdl5p0BAA%3D%3D&ccb=9-4&oh=00_AfO50xBN8iHU-iuOEUCLUQKYGvz0LMD9JB6NGB0qq-Wadg&oe=684AEFB8&_nc_sid=8b3546",
            "alt": null,
            "likesCount": 18,
            "videoViewCount": 0,
            "timestamp": "2025-06-04T14:15:53.000Z",
            "childPosts": [],
            "ownerUsername": "_urvashi_lalwani_",
            "ownerId": "32419739756",
            "productType": "clips",
            "isCommentsDisabled": false
        },
        {
            "id": "3646787704527550348",
            "type": "Image",
            "shortCode": "DKb_hiDoHeM",
            "caption": "Your skincare staple, now with a steal deal! \u2728\nGet up to 60% Off on Himalaya Purifying Neem Face Wash during the #FlipkartGlamUpSale!\n#TrendItFlipkartIt #FlipkartBeautySale #Himalaya\n@himalaya_facecare @flipkart @flipkartlifestyle",
            "hashtags": [
                "FlipkartGlamUpSale!",
                "TrendItFlipkartIt",
                "FlipkartBeautySale",
                "Himalaya"
            ],
            "mentions": [
                "himalaya_facecare",
                "flipkart",
                "flipkartlifestyle"
            ],
            "url": "https://www.instagram.com/p/DKb_hiDoHeM/",
            "commentsCount": 0,
            "dimensionsHeight": 1080,
            "dimensionsWidth": 1080,
            "displayUrl": "https://instagram.fbhk1-2.fna.fbcdn.net/v/t51.2885-15/503850028_18066300326083757_8108917733382700171_n.jpg?stp=dst-jpg_e15_fr_s1080x1080_tt6&_nc_ht=instagram.fbhk1-2.fna.fbcdn.net&_nc_cat=105&_nc_oc=Q6cZ2QHHpibXBwkkYREhypZpew140bZPQbx9vFpJmgGXlquy5XXQR0SASXlUhAxAvHtaiT0&_nc_ohc=WdFG-VKNg2AQ7kNvwHVFIDo&_nc_gid=e5mGv2vdFcvv89Ua151bSA&edm=AOQ1c0wBAAAA&ccb=7-5&ig_cache_key=MzY0Njc4NzcwNDUyNzU1MDM0OA%3D%3D.3-ccb7-5&oh=00_AfNqedWQSM9ISTawKK0b_quTAamN-D0PCA68H3O2gMHTQw&oe=684EDBA6&_nc_sid=8b3546",
            "images": [],
            "alt": "Photo by \ud835\ude50\ud835\ude67\ud835\ude6b\ud835\ude56\ud835\ude68\ud835\ude5d\ud835\ude5e \ud835\ude47\ud835\ude56\ud835\ude61\ud835\ude6c\ud835\ude56\ud835\ude63\ud835\ude5e on June 03, 2025. May be an image of hair product, ointment, cosmetics, lotion, hand cream and text that says 'Flipkart Glam up SALE Starts 6t June H\u0131malava\u00ae HENBALHEALTHGANE HERBAL HEALTHCARE Up to Upto60%Off 60% Off Himala SINCE Purifying Neem Face Prevenes PrevenesPimples Pimples F\u0131malaya SINCE Moisturizing AlopVeraa Face Wash AlonW HorealoDy 00 Neem+ Turmeric /Sas0 5\u03c3\u03c5 D3p-Free Paraen abvol 100mL'.",
            "likesCount": 2,
            "timestamp": "2025-06-03T11:43:13.000Z",
            "childPosts": [],
            "ownerUsername": "_urvashi_lalwani_",
            "ownerId": "32419739756",
            "isCommentsDisabled": false
        },
        {
            "id": "3646104729523687736",
            "type": "Video",
            "shortCode": "DKZkO8BIZE4",
            "caption": "Swatching 3 shades\u2728\nIt has very sheer tint.\nSuper glossy \nComes in 6 different shades\n.\n.\n.\n#laneige #glazecraze #laneigelip \n.\n(Laneige lip glaze swatches, Laneige lip glaze review, glossy lip swatches, new Laneige lip launch, best lip gloss for hydration, everyday lip gloss shades, non-sticky lip gloss, Korean beauty lip gloss, juicy lips look, lip gloss for Indian skin tone, tinted lip glaze, natural gloss finish, lip gloss for dry lips, shiny lips makeup trend, viral lip gloss 2025, lip gloss that feels like balm, glass lips effect, makeup swatches for brown skin, trending lip gloss shades, Laneige lip glaze on medium skin)",
            "hashtags": [
                "laneige",
                "glazecraze",
                "laneigelip"
            ],
            "mentions": [],
            "url": "https://www.instagram.com/p/DKZkO8BIZE4/",
            "commentsCount": 1,
            "dimensionsHeight": 1136,
            "dimensionsWidth": 640,
            "displayUrl": "https://instagram.fbhk1-3.fna.fbcdn.net/v/t51.2885-15/503325011_1032786015595684_7976317120147251218_n.jpg?stp=dst-jpg_e15_tt6&_nc_ht=instagram.fbhk1-3.fna.fbcdn.net&_nc_cat=104&_nc_oc=Q6cZ2QHHpibXBwkkYREhypZpew140bZPQbx9vFpJmgGXlquy5XXQR0SASXlUhAxAvHtaiT0&_nc_ohc=tsihpq7vr_sQ7kNvwFitEKP&_nc_gid=e5mGv2vdFcvv89Ua151bSA&edm=AOQ1c0wBAAAA&ccb=7-5&oh=00_AfMLw-AqCHdgLGuXcmfxtH6cWG83dvX_vD6zztQzAbfzxQ&oe=684EFEF2&_nc_sid=8b3546",
            "images": [],
            "videoUrl": "https://instagram.fbhk1-3.fna.fbcdn.net/o1/v/t16/f2/m86/AQMReArfTlFgsEQuw8rMX7D2_1nb8AfMsG9tHeudTX8qi2TFMzbHZABDrZNBfq4pcmS-rNgvVEVHinXYs0JzkbKY3aYNINT81oohmqI.mp4?stp=dst-mp4&efg=eyJxZV9ncm91cHMiOiJbXCJpZ193ZWJfZGVsaXZlcnlfdnRzX290ZlwiXSIsInZlbmNvZGVfdGFnIjoidnRzX3ZvZF91cmxnZW4uY2xpcHMuYzIuNzIwLmJhc2VsaW5lIn0&_nc_cat=104&vs=4122853714654767_2203844103&_nc_vs=HBksFQIYUmlnX3hwdl9yZWVsc19wZXJtYW5lbnRfc3JfcHJvZC81NTQ2OTM5M0JCRDE2REVBNTQwRkM3MzJCRkJBNkM4OF92aWRlb19kYXNoaW5pdC5tcDQVAALIARIAFQIYOnBhc3N0aHJvdWdoX2V2ZXJzdG9yZS9HUGpUQXg1TFM3aXZGLTBFQUQ3Z1E4eHk5MTFQYnFfRUFBQUYVAgLIARIAKAAYABsAFQAAJuStnriN2c8%2FFQIoAkMzLBdAN4hysCDEnBgSZGFzaF9iYXNlbGluZV8xX3YxEQB1%2FgdllqkBAA%3D%3D&ccb=9-4&oh=00_AfOQM9eUzHB_c_X-L4QeQ5SzOzE-k4GEQO6gmYhk-w6Ulg&oe=684B15ED&_nc_sid=8b3546",
            "alt": null,
            "likesCount": 19,
            "videoViewCount": 0,
            "timestamp": "2025-06-02T13:10:48.000Z",
            "childPosts": [],
            "ownerUsername": "_urvashi_lalwani_",
            "ownerId": "32419739756",
            "productType": "clips",
            "musicInfo": {
                "artist_name": "The Something Specials, Taylor Olin",
                "song_name": "Love",
                "uses_original_audio": false,
                "should_mute_audio": false,
                "should_mute_audio_reason": "",
                "audio_id": "1629255667608030"
            },
            "isCommentsDisabled": false
        },
        {
            "id": "3645447209222254991",
            "type": "Video",
            "shortCode": "DKXOuwhIbGP",
            "caption": "Get them today!",
            "hashtags": [],
            "mentions": [],
            "url": "https://www.instagram.com/p/DKXOuwhIbGP/",
            "commentsCount": 0,
            "dimensionsHeight": 1136,
            "dimensionsWidth": 640,
            "displayUrl": "https://instagram.fbhk1-2.fna.fbcdn.net/v/t51.2885-15/502250186_689863203781017_3706253479976977269_n.jpg?stp=dst-jpg_e15_tt6&_nc_ht=instagram.fbhk1-2.fna.fbcdn.net&_nc_cat=109&_nc_oc=Q6cZ2QHHpibXBwkkYREhypZpew140bZPQbx9vFpJmgGXlquy5XXQR0SASXlUhAxAvHtaiT0&_nc_ohc=Hb0P8M6q-sIQ7kNvwHfFUWK&_nc_gid=e5mGv2vdFcvv89Ua151bSA&edm=AOQ1c0wBAAAA&ccb=7-5&oh=00_AfPHAYV6EBToVpwBa9BZYzggQCimx-r2_Ymg8zilOyshVA&oe=684F0891&_nc_sid=8b3546",
            "images": [],
            "videoUrl": "https://instagram.fbhk1-3.fna.fbcdn.net/o1/v/t16/f2/m86/AQOqS69k2esMXaxxMP4xagNcb4_FnkN9yTZsme2ZvC7zJXK31z-VPx9WIs6J9CnkKgER4leRFX-8lkXQ88UA0aBCeAryDYgYKvgL0VY.mp4?stp=dst-mp4&efg=eyJxZV9ncm91cHMiOiJbXCJpZ193ZWJfZGVsaXZlcnlfdnRzX290ZlwiXSIsInZlbmNvZGVfdGFnIjoidnRzX3ZvZF91cmxnZW4uY2xpcHMuYzIuNzIwLmJhc2VsaW5lIn0&_nc_cat=104&vs=1109415247683143_2840255213&_nc_vs=HBksFQIYUmlnX3hwdl9yZWVsc19wZXJtYW5lbnRfc3JfcHJvZC9ENDQyQTAwOTA1NjUyQUNBRkFDMkM1RTJCQTU4MzBCRV92aWRlb19kYXNoaW5pdC5tcDQVAALIARIAFQIYOnBhc3N0aHJvdWdoX2V2ZXJzdG9yZS9HQVp4OUIwdXVWSDE0RVFDQUh5eHM5VzNkbjBEYnFfRUFBQUYVAgLIARIAKAAYABsAFQAAJuSv8pnt0s8%2FFQIoAkMzLBdAR93S8an75xgSZGFzaF9iYXNlbGluZV8xX3YxEQB1%2Fgdl5p0BAA%3D%3D&ccb=9-4&oh=00_AfPsx1Ca352ySOMeBsrhknPGe2wPjesW2auySGAtezSHCw&oe=684B09CB&_nc_sid=8b3546",
            "alt": null,
            "likesCount": 16,
            "videoViewCount": 0,
            "timestamp": "2025-06-01T15:23:39.000Z",
            "childPosts": [],
            "ownerUsername": "_urvashi_lalwani_",
            "ownerId": "32419739756",
            "productType": "clips",
            "taggedUsers": [
                {
                    "full_name": "WOMENHOOD\u00ae",
                    "id": "48319015880",
                    "is_verified": false,
                    "profile_pic_url": "https://instagram.fbhk1-3.fna.fbcdn.net/v/t51.2885-19/480734429_3602898653336871_4401707907292130271_n.jpg?stp=dst-jpg_e0_s150x150_tt6&_nc_ht=instagram.fbhk1-3.fna.fbcdn.net&_nc_cat=103&_nc_oc=Q6cZ2QHHpibXBwkkYREhypZpew140bZPQbx9vFpJmgGXlquy5XXQR0SASXlUhAxAvHtaiT0&_nc_ohc=sxKfMTdR3j0Q7kNvwFmy5Ml&_nc_gid=e5mGv2vdFcvv89Ua151bSA&edm=AOQ1c0wBAAAA&ccb=7-5&oh=00_AfPbNDhBKnb1JfAYUIYwutA6kJ1r03_rhS-H1MPx4jvDvA&oe=684EDD9C&_nc_sid=8b3546",
                    "username": "womenhood.korea"
                }
            ],
            "isCommentsDisabled": false
        },
        {
            "id": "3644599966474911237",
            "type": "Video",
            "shortCode": "DKUOFwOIz4F",
            "caption": "Do we like it?\nComment \u201cBAG\u201d for the \ud83d\udd17\n.\n.\n.\n.\n.\n.\n.\n.\n.\n.\n.\n.\n[Meesho bags, affordable bags, best Meesho bags, budget-friendly bags, bags under 300, stylish bags, trendy bags, shoulder bags, tote bags, sling bags, best bag finds, handbag collection, cute bags, everyday bags, must-have bags, fashionable bags, quality bags, affordable fashion, bag shopping, budget buys]\n.\n#meeshobags #meeshofinds",
            "hashtags": [
                "meeshobags",
                "meeshofinds"
            ],
            "mentions": [],
            "url": "https://www.instagram.com/p/DKUOFwOIz4F/",
            "commentsCount": 7,
            "dimensionsHeight": 1136,
            "dimensionsWidth": 640,
            "displayUrl": "https://instagram.fbhk1-4.fna.fbcdn.net/v/t51.2885-15/503106674_1328676121551650_6815920742665219235_n.jpg?stp=dst-jpg_e15_tt6&_nc_ht=instagram.fbhk1-4.fna.fbcdn.net&_nc_cat=102&_nc_oc=Q6cZ2QHHpibXBwkkYREhypZpew140bZPQbx9vFpJmgGXlquy5XXQR0SASXlUhAxAvHtaiT0&_nc_ohc=dcoc1E95ArYQ7kNvwHNC54F&_nc_gid=e5mGv2vdFcvv89Ua151bSA&edm=AOQ1c0wBAAAA&ccb=7-5&oh=00_AfPzzb9goNRG855FgBCgA-iHcP8_R8q4byNsPAoCWfSvXg&oe=684EFEA4&_nc_sid=8b3546",
            "images": [],
            "videoUrl": "https://instagram.fbhk1-3.fna.fbcdn.net/o1/v/t16/f2/m86/AQNQU2MY4-QwQJiu0kGABf6-sUpSP4WG_M7LVtQZ59UmKHqOAb570P-CXp9a-6fJ5PbemAY-Z9fPvQpCPjEqyw9Z1F3-GSSsktD3loY.mp4?stp=dst-mp4&efg=eyJxZV9ncm91cHMiOiJbXCJpZ193ZWJfZGVsaXZlcnlfdnRzX290ZlwiXSIsInZlbmNvZGVfdGFnIjoidnRzX3ZvZF91cmxnZW4uY2xpcHMuYzIuNzIwLmJhc2VsaW5lIn0&_nc_cat=100&vs=866836835659270_1396472696&_nc_vs=HBksFQIYUmlnX3hwdl9yZWVsc19wZXJtYW5lbnRfc3JfcHJvZC82MTQxMTg0NEVBRkJFNEJDQTZBOURGQjA3OUZBNEI4MV92aWRlb19kYXNoaW5pdC5tcDQVAALIARIAFQIYOnBhc3N0aHJvdWdoX2V2ZXJzdG9yZS9HRlBMOEIyQ0NCR25lV3NDQURtRDhwUngxTkFzYnFfRUFBQUYVAgLIARIAKAAYABsAFQAAJuT874L2yc8%2FFQIoAkMzLBdAMlU%2FfO2RaBgSZGFzaF9iYXNlbGluZV8xX3YxEQB1%2Fgdl5p0BAA%3D%3D&ccb=9-4&oh=00_AfOSiSyBHRuS0xQ2HZQrXxT5tXbSA-3mAgftJ87bAeQ_Ww&oe=684B01E8&_nc_sid=8b3546",
            "alt": null,
            "likesCount": 23,
            "videoViewCount": 0,
            "timestamp": "2025-05-31T11:18:52.000Z",
            "childPosts": [],
            "ownerUsername": "_urvashi_lalwani_",
            "ownerId": "32419739756",
            "productType": "clips",
            "musicInfo": {
                "artist_name": "Bad Bunny",
                "song_name": "NUEVAYoL",
                "uses_original_audio": false,
                "should_mute_audio": false,
                "should_mute_audio_reason": "",
                "audio_id": "1524117734944675"
            },
            "isCommentsDisabled": false
        }
    ],
    "fbid": "17841432512682467"
}